{
"meta":{"test_sets":[],"test_metrics":[],"learn_metrics":[{"best_value":"Min","name":"MultiClass"}],"launch_mode":"Train","parameters":"","iteration_count":1000,"learn_sets":["learn"],"name":"experiment"},
"iterations":[
{"learn":[3.288812777],"iteration":0,"passed_time":0.05457333697,"remaining_time":54.51876363},
{"learn":[2.887004048],"iteration":1,"passed_time":0.1081535401,"remaining_time":53.96861651},
{"learn":[2.563414562],"iteration":2,"passed_time":0.1608094136,"remaining_time":53.44232845},
{"learn":[2.350820466],"iteration":3,"passed_time":0.227698291,"remaining_time":56.69687446},
{"learn":[2.191767521],"iteration":4,"passed_time":0.29305878,"remaining_time":58.31869723},
{"learn":[2.05848683],"iteration":5,"passed_time":0.3676184037,"remaining_time":60.90211555},
{"learn":[1.888999304],"iteration":6,"passed_time":0.4264598696,"remaining_time":60.49637864},
{"learn":[1.781865255],"iteration":7,"passed_time":0.4812987674,"remaining_time":59.68104716},
{"learn":[1.67968052],"iteration":8,"passed_time":0.5398820876,"remaining_time":59.44701654},
{"learn":[1.581788655],"iteration":9,"passed_time":0.5893982342,"remaining_time":58.35042519},
{"learn":[1.512319851],"iteration":10,"passed_time":0.6448495898,"remaining_time":57.97784039},
{"learn":[1.458082461],"iteration":11,"passed_time":0.7123246409,"remaining_time":58.6480621},
{"learn":[1.389428373],"iteration":12,"passed_time":0.7738786168,"remaining_time":58.75524575},
{"learn":[1.335397576],"iteration":13,"passed_time":0.8384470681,"remaining_time":59.05062922},
{"learn":[1.242502572],"iteration":14,"passed_time":0.9082328388,"remaining_time":59.64062308},
{"learn":[1.187814457],"iteration":15,"passed_time":0.9686162961,"remaining_time":59.56990221},
{"learn":[1.153853129],"iteration":16,"passed_time":1.021208596,"remaining_time":59.04988529},
{"learn":[1.090654589],"iteration":17,"passed_time":1.077858385,"remaining_time":58.803163},
{"learn":[1.048516719],"iteration":18,"passed_time":1.127172356,"remaining_time":58.1976885},
{"learn":[0.9870155163],"iteration":19,"passed_time":1.186454584,"remaining_time":58.13627463},
{"learn":[0.9609016699],"iteration":20,"passed_time":1.234671669,"remaining_time":57.55921731},
{"learn":[0.9355006859],"iteration":21,"passed_time":1.280685934,"remaining_time":56.93231105},
{"learn":[0.9127019957],"iteration":22,"passed_time":1.346713394,"remaining_time":57.20604285},
{"learn":[0.8754810169],"iteration":23,"passed_time":1.395828666,"remaining_time":56.7636991},
{"learn":[0.8509798207],"iteration":24,"passed_time":1.444142922,"remaining_time":56.32157396},
{"learn":[0.8146737544],"iteration":25,"passed_time":1.491572712,"remaining_time":55.87660851},
{"learn":[0.7901643986],"iteration":26,"passed_time":1.537577307,"remaining_time":55.40973035},
{"learn":[0.7712976537],"iteration":27,"passed_time":1.592015452,"remaining_time":55.26567927},
{"learn":[0.751374924],"iteration":28,"passed_time":1.642450946,"remaining_time":54.99378856},
{"learn":[0.7320221942],"iteration":29,"passed_time":1.691207593,"remaining_time":54.68237886},
{"learn":[0.7142045931],"iteration":30,"passed_time":1.741331596,"remaining_time":54.43065536},
{"learn":[0.6972973086],"iteration":31,"passed_time":1.788396573,"remaining_time":54.09899632},
{"learn":[0.6806345981],"iteration":32,"passed_time":1.841147138,"remaining_time":53.95119039},
{"learn":[0.6651715386],"iteration":33,"passed_time":1.88945054,"remaining_time":53.68262417},
{"learn":[0.6288677339],"iteration":34,"passed_time":1.948295856,"remaining_time":53.71730003},
{"learn":[0.610158315],"iteration":35,"passed_time":2.005641295,"remaining_time":53.7066169},
{"learn":[0.5977214209],"iteration":36,"passed_time":2.066060829,"remaining_time":53.77342103},
{"learn":[0.5693510612],"iteration":37,"passed_time":2.123783125,"remaining_time":53.76524648},
{"learn":[0.5548492006],"iteration":38,"passed_time":2.175629348,"remaining_time":53.60973854},
{"learn":[0.5416389124],"iteration":39,"passed_time":2.231948758,"remaining_time":53.56677019},
{"learn":[0.5221847965],"iteration":40,"passed_time":2.286836694,"remaining_time":53.48966803},
{"learn":[0.4965206181],"iteration":41,"passed_time":2.355332436,"remaining_time":53.72401128},
{"learn":[0.4857233929],"iteration":42,"passed_time":2.401098632,"remaining_time":53.43840443},
{"learn":[0.475633232],"iteration":43,"passed_time":2.447430554,"remaining_time":53.17599113},
{"learn":[0.4666297509],"iteration":44,"passed_time":2.488489814,"remaining_time":52.81128382},
{"learn":[0.457301389],"iteration":45,"passed_time":2.536159085,"remaining_time":52.59773407},
{"learn":[0.4489353633],"iteration":46,"passed_time":2.584425616,"remaining_time":52.40335345},
{"learn":[0.4379216826],"iteration":47,"passed_time":2.644473313,"remaining_time":52.44872071},
{"learn":[0.4187266639],"iteration":48,"passed_time":2.692031711,"remaining_time":52.24739097},
{"learn":[0.4097100502],"iteration":49,"passed_time":2.745999912,"remaining_time":52.17399833},
{"learn":[0.3901444036],"iteration":50,"passed_time":2.815835739,"remaining_time":52.39662973},
{"learn":[0.3798912593],"iteration":51,"passed_time":2.883497217,"remaining_time":52.56837233},
{"learn":[0.3719271373],"iteration":52,"passed_time":2.94393582,"remaining_time":52.60202304},
{"learn":[0.3641458995],"iteration":53,"passed_time":3.000528691,"remaining_time":52.56481744},
{"learn":[0.3553518725],"iteration":54,"passed_time":3.050834463,"remaining_time":52.41888305},
{"learn":[0.3428867472],"iteration":55,"passed_time":3.103065635,"remaining_time":52.3088207},
{"learn":[0.336994583],"iteration":56,"passed_time":3.153842569,"remaining_time":52.17672881},
{"learn":[0.320582761],"iteration":57,"passed_time":3.20960579,"remaining_time":52.12842507},
{"learn":[0.3127650517],"iteration":58,"passed_time":3.276918444,"remaining_time":52.26407214},
{"learn":[0.3065879162],"iteration":59,"passed_time":3.344963494,"remaining_time":52.40442807},
{"learn":[0.2928297892],"iteration":60,"passed_time":3.395763307,"remaining_time":52.27248762},
{"learn":[0.2861576088],"iteration":61,"passed_time":3.444937377,"remaining_time":52.11856871},
{"learn":[0.2760759495],"iteration":62,"passed_time":3.495153829,"remaining_time":51.98347838},
{"learn":[0.2664848487],"iteration":63,"passed_time":3.542660882,"remaining_time":51.81141539},
{"learn":[0.2592071678],"iteration":64,"passed_time":3.585853687,"remaining_time":51.58112611},
{"learn":[0.2545779689],"iteration":65,"passed_time":3.632086379,"remaining_time":51.39952542},
{"learn":[0.2439537194],"iteration":66,"passed_time":3.682814803,"remaining_time":51.28457031},
{"learn":[0.2338216126],"iteration":67,"passed_time":3.732186399,"remaining_time":51.1529077},
{"learn":[0.2286439989],"iteration":68,"passed_time":3.780886288,"remaining_time":51.01456716},
{"learn":[0.2212174325],"iteration":69,"passed_time":3.83101875,"remaining_time":50.89782053},
{"learn":[0.2172844578],"iteration":70,"passed_time":3.878043236,"remaining_time":50.74228404},
{"learn":[0.211937555],"iteration":71,"passed_time":3.925123821,"remaining_time":50.59048481},
{"learn":[0.2031165721],"iteration":72,"passed_time":3.975460898,"remaining_time":50.48290756},
{"learn":[0.1969230052],"iteration":73,"passed_time":4.027473022,"remaining_time":50.39783809},
{"learn":[0.1893109506],"iteration":74,"passed_time":4.069170141,"remaining_time":50.18643174},
{"learn":[0.184754293],"iteration":75,"passed_time":4.115069807,"remaining_time":50.03058554},
{"learn":[0.1798160067],"iteration":76,"passed_time":4.159798961,"remaining_time":49.86356417},
{"learn":[0.176155389],"iteration":77,"passed_time":4.204219103,"remaining_time":49.6960258},
{"learn":[0.1733592934],"iteration":78,"passed_time":4.255341438,"remaining_time":49.60974006},
{"learn":[0.1675418066],"iteration":79,"passed_time":4.312069304,"remaining_time":49.588797},
{"learn":[0.1651198641],"iteration":80,"passed_time":4.366758771,"remaining_time":49.54384334},
{"learn":[0.1622065158],"iteration":81,"passed_time":4.421516779,"remaining_time":49.49941955},
{"learn":[0.1561857578],"iteration":82,"passed_time":4.505792753,"remaining_time":49.78086692},
{"learn":[0.153648533],"iteration":83,"passed_time":4.573911877,"remaining_time":49.87741999},
{"learn":[0.1512494565],"iteration":84,"passed_time":4.621095165,"remaining_time":49.74473031},
{"learn":[0.1489775629],"iteration":85,"passed_time":4.663087669,"remaining_time":49.55886197},
{"learn":[0.1440289059],"iteration":86,"passed_time":4.708536637,"remaining_time":49.41257413},
{"learn":[0.1415893052],"iteration":87,"passed_time":4.755119012,"remaining_time":49.2803243},
{"learn":[0.1397567806],"iteration":88,"passed_time":4.801844859,"remaining_time":49.15146817},
{"learn":[0.1378006982],"iteration":89,"passed_time":4.853339057,"remaining_time":49.07265047},
{"learn":[0.1352747839],"iteration":90,"passed_time":4.912027198,"remaining_time":49.06629366},
{"learn":[0.1307762206],"iteration":91,"passed_time":4.981647372,"remaining_time":49.16669363},
{"learn":[0.1276403695],"iteration":92,"passed_time":5.043898917,"remaining_time":49.1915733},
{"learn":[0.1238671831],"iteration":93,"passed_time":5.100751533,"remaining_time":49.16256265},
{"learn":[0.1223607917],"iteration":94,"passed_time":5.170441284,"remaining_time":49.25525644},
{"learn":[0.1200953301],"iteration":95,"passed_time":5.229415024,"remaining_time":49.24365814},
{"learn":[0.117913511],"iteration":96,"passed_time":5.284036268,"remaining_time":49.19056443},
{"learn":[0.1163605438],"iteration":97,"passed_time":5.341073418,"remaining_time":49.15967574},
{"learn":[0.1140401477],"iteration":98,"passed_time":5.392389732,"remaining_time":49.07619342},
{"learn":[0.1124165093],"iteration":99,"passed_time":5.449508281,"remaining_time":49.04557453},
{"learn":[0.1096041396],"iteration":100,"passed_time":5.500098675,"remaining_time":48.95632385},
{"learn":[0.1075711526],"iteration":101,"passed_time":5.556470628,"remaining_time":48.91873161},
{"learn":[0.1048542222],"iteration":102,"passed_time":5.613557143,"remaining_time":48.88699765},
{"learn":[0.1033906906],"iteration":103,"passed_time":5.722867321,"remaining_time":49.30470307},
{"learn":[0.1022372144],"iteration":104,"passed_time":5.791694421,"remaining_time":49.36730006},
{"learn":[0.09938540411],"iteration":105,"passed_time":5.91917258,"remaining_time":49.92207817},
{"learn":[0.09621995542],"iteration":106,"passed_time":6.018624591,"remaining_time":50.23020336},
{"learn":[0.09391875865],"iteration":107,"passed_time":6.114171717,"remaining_time":50.49852937},
{"learn":[0.09245886663],"iteration":108,"passed_time":6.202479928,"remaining_time":50.70100565},
{"learn":[0.09084777045],"iteration":109,"passed_time":6.292576311,"remaining_time":50.91266288},
{"learn":[0.08835424692],"iteration":110,"passed_time":6.371208725,"remaining_time":51.02706808},
{"learn":[0.08560464642],"iteration":111,"passed_time":6.438650836,"remaining_time":51.04930306},
{"learn":[0.08443314723],"iteration":112,"passed_time":6.515336409,"remaining_time":51.14250792},
{"learn":[0.08284920813],"iteration":113,"passed_time":6.588277918,"remaining_time":51.20363364},
{"learn":[0.08131955791],"iteration":114,"passed_time":6.655238133,"remaining_time":51.21639781},
{"learn":[0.0794121641],"iteration":115,"passed_time":6.721944646,"remaining_time":51.22585403},
{"learn":[0.07752201364],"iteration":116,"passed_time":6.788525812,"remaining_time":51.23306232},
{"learn":[0.07670574972],"iteration":117,"passed_time":6.85518185,"remaining_time":51.23957959},
{"learn":[0.07554098048],"iteration":118,"passed_time":6.925026858,"remaining_time":51.26847615},
{"learn":[0.07406091438],"iteration":119,"passed_time":6.985884422,"remaining_time":51.2298191},
{"learn":[0.07340568842],"iteration":120,"passed_time":7.061407942,"remaining_time":51.29733538},
{"learn":[0.07166898433],"iteration":121,"passed_time":7.136964558,"remaining_time":51.36274494},
{"learn":[0.07065004787],"iteration":122,"passed_time":7.198020784,"remaining_time":51.3224734},
{"learn":[0.06966492408],"iteration":123,"passed_time":7.26305753,"remaining_time":51.30998707},
{"learn":[0.06822422335],"iteration":124,"passed_time":7.332388504,"remaining_time":51.32671952},
{"learn":[0.06714520937],"iteration":125,"passed_time":7.394289623,"remaining_time":51.29054866},
{"learn":[0.06568911078],"iteration":126,"passed_time":7.463116795,"remaining_time":51.30158237},
{"learn":[0.06488532384],"iteration":127,"passed_time":7.526017963,"remaining_time":51.27099737},
{"learn":[0.06414048732],"iteration":128,"passed_time":7.596419401,"remaining_time":51.2905527},
{"learn":[0.06349217318],"iteration":129,"passed_time":7.660205347,"remaining_time":51.26445117},
{"learn":[0.06224018044],"iteration":130,"passed_time":7.727993104,"remaining_time":51.26432067},
{"learn":[0.06160026436],"iteration":131,"passed_time":7.855634881,"remaining_time":51.65675058},
{"learn":[0.06015440588],"iteration":132,"passed_time":7.915539624,"remaining_time":51.5997959},
{"learn":[0.05957348064],"iteration":133,"passed_time":7.989333875,"remaining_time":51.63256072},
{"learn":[0.05893383471],"iteration":134,"passed_time":8.073681126,"remaining_time":51.73136425},
{"learn":[0.05829965442],"iteration":135,"passed_time":8.139497815,"remaining_time":51.70975083},
{"learn":[0.05688817202],"iteration":136,"passed_time":8.213229453,"remaining_time":51.7373505},
{"learn":[0.05634939166],"iteration":137,"passed_time":8.29128612,"remaining_time":51.79049736},
{"learn":[0.05546880691],"iteration":138,"passed_time":8.356555793,"remaining_time":51.76255063},
{"learn":[0.05483639943],"iteration":139,"passed_time":8.413249682,"remaining_time":51.68139091},
{"learn":[0.0542957953],"iteration":140,"passed_time":8.485872574,"remaining_time":51.69762086},
{"learn":[0.05311265382],"iteration":141,"passed_time":8.545934795,"remaining_time":51.63670461},
{"learn":[0.05255684609],"iteration":142,"passed_time":8.609560713,"remaining_time":51.59715756},
{"learn":[0.05188113782],"iteration":143,"passed_time":8.667587739,"remaining_time":51.52399378},
{"learn":[0.05082529091],"iteration":144,"passed_time":8.725218361,"remaining_time":51.44870137},
{"learn":[0.05033112797],"iteration":145,"passed_time":8.784529154,"remaining_time":51.38347875},
{"learn":[0.04957430814],"iteration":146,"passed_time":8.844488656,"remaining_time":51.32210084},
{"learn":[0.04881267969],"iteration":147,"passed_time":8.912399092,"remaining_time":51.30651369},
{"learn":[0.0479717657],"iteration":148,"passed_time":8.985853614,"remaining_time":51.32188876},
{"learn":[0.04724209519],"iteration":149,"passed_time":9.047227648,"remaining_time":51.26762334},
{"learn":[0.04658306517],"iteration":150,"passed_time":9.111789742,"remaining_time":51.23118868},
{"learn":[0.04587161788],"iteration":151,"passed_time":9.17570909,"remaining_time":51.19079808},
{"learn":[0.04517021329],"iteration":152,"passed_time":9.238332464,"remaining_time":51.14292547},
{"learn":[0.04460864674],"iteration":153,"passed_time":9.305325726,"remaining_time":51.1188673},
{"learn":[0.0439384938],"iteration":154,"passed_time":9.370135035,"remaining_time":51.08234906},
{"learn":[0.04295159148],"iteration":155,"passed_time":9.433854242,"remaining_time":51.03957039},
{"learn":[0.04239623203],"iteration":156,"passed_time":9.50006974,"remaining_time":51.0099286},
{"learn":[0.04187074902],"iteration":157,"passed_time":9.560608721,"remaining_time":50.94957306},
{"learn":[0.04125002484],"iteration":158,"passed_time":9.635773325,"remaining_time":50.96657463},
{"learn":[0.04089576627],"iteration":159,"passed_time":9.716636227,"remaining_time":51.01234019},
{"learn":[0.04013227178],"iteration":160,"passed_time":9.791261858,"remaining_time":51.02402918},
{"learn":[0.03980279525],"iteration":161,"passed_time":9.851975006,"remaining_time":50.96268553},
{"learn":[0.03923311263],"iteration":162,"passed_time":9.91169704,"remaining_time":50.89626026},
{"learn":[0.03845996281],"iteration":163,"passed_time":9.972128419,"remaining_time":50.83353267},
{"learn":[0.03789736097],"iteration":164,"passed_time":10.0356936,"remaining_time":50.78669185},
{"learn":[0.03744348457],"iteration":165,"passed_time":10.09848804,"remaining_time":50.73577725},
{"learn":[0.03713463327],"iteration":166,"passed_time":10.15379657,"remaining_time":50.64738049},
{"learn":[0.03677597454],"iteration":167,"passed_time":10.21929207,"remaining_time":50.60982739},
{"learn":[0.03641797685],"iteration":168,"passed_time":10.28535574,"remaining_time":50.5747374},
{"learn":[0.03615074922],"iteration":169,"passed_time":10.34742191,"remaining_time":50.5197658},
{"learn":[0.03571030675],"iteration":170,"passed_time":10.41934399,"remaining_time":50.51249219},
{"learn":[0.03529550258],"iteration":171,"passed_time":10.50110284,"remaining_time":50.55182067},
{"learn":[0.03502749387],"iteration":172,"passed_time":10.57621615,"remaining_time":50.55798126},
{"learn":[0.03480101457],"iteration":173,"passed_time":10.6451241,"remaining_time":50.53375004},
{"learn":[0.0342476075],"iteration":174,"passed_time":10.72054851,"remaining_time":50.53972868},
{"learn":[0.03371106225],"iteration":175,"passed_time":10.79779253,"remaining_time":50.55330137},
{"learn":[0.03329894841],"iteration":176,"passed_time":10.86337371,"remaining_time":50.51161901},
{"learn":[0.03299669046],"iteration":177,"passed_time":10.93222355,"remaining_time":50.48476267},
{"learn":[0.03273994502],"iteration":178,"passed_time":10.99612911,"remaining_time":50.43475976},
{"learn":[0.03245580707],"iteration":179,"passed_time":11.05889037,"remaining_time":50.37938946},
{"learn":[0.03212651468],"iteration":180,"passed_time":11.12611809,"remaining_time":50.3441476},
{"learn":[0.03163265665],"iteration":181,"passed_time":11.19306905,"remaining_time":50.30731034},
{"learn":[0.03141704361],"iteration":182,"passed_time":11.26187702,"remaining_time":50.27843458},
{"learn":[0.03118981302],"iteration":183,"passed_time":11.32367863,"remaining_time":50.21805307},
{"learn":[0.03097589967],"iteration":184,"passed_time":11.39256568,"remaining_time":50.18887043},
{"learn":[0.03072029424],"iteration":185,"passed_time":11.45356993,"remaining_time":50.12476305},
{"learn":[0.03031831664],"iteration":186,"passed_time":11.51432764,"remaining_time":50.05961695},
{"learn":[0.03009707091],"iteration":187,"passed_time":11.57559511,"remaining_time":49.99671933},
{"learn":[0.02973129078],"iteration":188,"passed_time":11.63918797,"remaining_time":49.94381717},
{"learn":[0.02956621759],"iteration":189,"passed_time":11.70263879,"remaining_time":49.89019695},
{"learn":[0.02938318995],"iteration":190,"passed_time":11.76096564,"remaining_time":49.81477068},
{"learn":[0.02901220436],"iteration":191,"passed_time":11.82178681,"remaining_time":49.75001948},
{"learn":[0.0287109466],"iteration":192,"passed_time":11.87786844,"remaining_time":49.66549136},
{"learn":[0.02829320589],"iteration":193,"passed_time":11.94025507,"remaining_time":49.60745146},
{"learn":[0.02792778525],"iteration":194,"passed_time":11.99346037,"remaining_time":49.51146462},
{"learn":[0.0277300276],"iteration":195,"passed_time":12.0562613,"remaining_time":49.45527595},
{"learn":[0.02749508842],"iteration":196,"passed_time":12.11212089,"remaining_time":49.37072625},
{"learn":[0.02729858363],"iteration":197,"passed_time":12.17639481,"remaining_time":49.32054867},
{"learn":[0.02706180089],"iteration":198,"passed_time":12.24057318,"remaining_time":49.26984482},
{"learn":[0.02683054375],"iteration":199,"passed_time":12.30434031,"remaining_time":49.21736122},
{"learn":[0.02646556729],"iteration":200,"passed_time":12.35973197,"remaining_time":49.13147187},
{"learn":[0.02621514522],"iteration":201,"passed_time":12.42132171,"remaining_time":49.07036991},
{"learn":[0.02595589359],"iteration":202,"passed_time":12.48557941,"remaining_time":49.01973788},
{"learn":[0.02578494252],"iteration":203,"passed_time":12.54860104,"remaining_time":48.96414917},
{"learn":[0.0255312411],"iteration":204,"passed_time":12.60894076,"remaining_time":48.89808736},
{"learn":[0.0253925845],"iteration":205,"passed_time":12.67569247,"remaining_time":48.85679523},
{"learn":[0.02523942915],"iteration":206,"passed_time":12.75534965,"remaining_time":48.86469695},
{"learn":[0.02495788973],"iteration":207,"passed_time":12.82835625,"remaining_time":48.8464334},
{"learn":[0.0247725965],"iteration":208,"passed_time":12.91028178,"remaining_time":48.86140136},
{"learn":[0.02464854042],"iteration":209,"passed_time":12.99267801,"remaining_time":48.87721728},
{"learn":[0.0245064087],"iteration":210,"passed_time":13.07638564,"remaining_time":48.897006},
{"learn":[0.02436648201],"iteration":211,"passed_time":13.15296454,"remaining_time":48.88932104},
{"learn":[0.02414897506],"iteration":212,"passed_time":13.23004435,"remaining_time":48.88283993},
{"learn":[0.02391569598],"iteration":213,"passed_time":13.29875174,"remaining_time":48.84494797},
{"learn":[0.02373985607],"iteration":214,"passed_time":13.35216685,"remaining_time":48.75093478},
{"learn":[0.02355800508],"iteration":215,"passed_time":13.43502243,"remaining_time":48.76415549},
{"learn":[0.02337360966],"iteration":216,"passed_time":13.51431893,"remaining_time":48.7636485},
{"learn":[0.02320808076],"iteration":217,"passed_time":13.57872389,"remaining_time":48.70900039},
{"learn":[0.02299758998],"iteration":218,"passed_time":13.64632231,"remaining_time":48.66565171},
{"learn":[0.02273117693],"iteration":219,"passed_time":13.71532657,"remaining_time":48.62706692},
{"learn":[0.02256848747],"iteration":220,"passed_time":13.77694478,"remaining_time":48.56217186},
{"learn":[0.02232921747],"iteration":221,"passed_time":13.88300155,"remaining_time":48.65304147},
{"learn":[0.02219090348],"iteration":222,"passed_time":13.99075721,"remaining_time":48.74806435},
{"learn":[0.02198762124],"iteration":223,"passed_time":14.10827802,"remaining_time":48.875106},
{"learn":[0.02188602114],"iteration":224,"passed_time":14.18298893,"remaining_time":48.85251744},
{"learn":[0.02174678053],"iteration":225,"passed_time":14.25354792,"remaining_time":48.81524817},
{"learn":[0.02157462489],"iteration":226,"passed_time":14.32836281,"remaining_time":48.79217821},
{"learn":[0.02137811947],"iteration":227,"passed_time":14.3903407,"remaining_time":48.72518868},
{"learn":[0.02111282666],"iteration":228,"passed_time":14.46203565,"remaining_time":48.69095845},
{"learn":[0.02084570532],"iteration":229,"passed_time":14.53253028,"remaining_time":48.65238399},
{"learn":[0.0206982223],"iteration":230,"passed_time":14.5936819,"remaining_time":48.58243024},
{"learn":[0.02053781555],"iteration":231,"passed_time":14.65288573,"remaining_time":48.50610448},
{"learn":[0.02041604921],"iteration":232,"passed_time":14.71975861,"remaining_time":48.45517104},
{"learn":[0.02026244801],"iteration":233,"passed_time":14.77845459,"remaining_time":48.37733424},
{"learn":[0.02012483874],"iteration":234,"passed_time":14.84040198,"remaining_time":48.31024474},
{"learn":[0.01998406232],"iteration":235,"passed_time":14.90401,"remaining_time":48.24857476},
{"learn":[0.01982186636],"iteration":236,"passed_time":14.97003007,"remaining_time":48.19465377},
{"learn":[0.01971766722],"iteration":237,"passed_time":15.02586125,"remaining_time":48.10800956},
{"learn":[0.01953535181],"iteration":238,"passed_time":15.08773605,"remaining_time":48.04086667},
{"learn":[0.01937117754],"iteration":239,"passed_time":15.15262291,"remaining_time":47.98330588},
{"learn":[0.01926775962],"iteration":240,"passed_time":15.22232332,"remaining_time":47.94084399},
{"learn":[0.01916796222],"iteration":241,"passed_time":15.27546429,"remaining_time":47.84628898},
{"learn":[0.01892772908],"iteration":242,"passed_time":15.33858584,"remaining_time":47.7831666},
{"learn":[0.01880560714],"iteration":243,"passed_time":15.39207389,"remaining_time":47.69019614},
{"learn":[0.01870301951],"iteration":244,"passed_time":15.46778476,"remaining_time":47.6660306},
{"learn":[0.01859050459],"iteration":245,"passed_time":15.53618864,"remaining_time":47.61904973},
{"learn":[0.01847605896],"iteration":246,"passed_time":15.60635082,"remaining_time":47.57725573},
{"learn":[0.01837019849],"iteration":247,"passed_time":15.67345765,"remaining_time":47.52596837},
{"learn":[0.01822697644],"iteration":248,"passed_time":15.75099976,"remaining_time":47.5060274},
{"learn":[0.01808090378],"iteration":249,"passed_time":15.81782617,"remaining_time":47.45347851},
{"learn":[0.01799341234],"iteration":250,"passed_time":15.87860398,"remaining_time":47.38276646},
{"learn":[0.01790827531],"iteration":251,"passed_time":15.94378159,"remaining_time":47.32519297},
{"learn":[0.01772545039],"iteration":252,"passed_time":16.00487897,"remaining_time":47.2555122},
{"learn":[0.01754664997],"iteration":253,"passed_time":16.06652132,"remaining_time":47.18749961},
{"learn":[0.01736133259],"iteration":254,"passed_time":16.13180631,"remaining_time":47.13017921},
{"learn":[0.01726449313],"iteration":255,"passed_time":16.18823457,"remaining_time":47.04705671},
{"learn":[0.0171347369],"iteration":256,"passed_time":16.25378996,"remaining_time":46.99052894},
{"learn":[0.01697564526],"iteration":257,"passed_time":16.31887292,"remaining_time":46.9325725},
{"learn":[0.01687516883],"iteration":258,"passed_time":16.37329979,"remaining_time":46.84407392},
{"learn":[0.01681860238],"iteration":259,"passed_time":16.43613135,"remaining_time":46.77975847},
{"learn":[0.01672425005],"iteration":260,"passed_time":16.49753867,"remaining_time":46.71142175},
{"learn":[0.01660698331],"iteration":261,"passed_time":16.5692413,"remaining_time":46.67213772},
{"learn":[0.01647554718],"iteration":262,"passed_time":16.6500752,"remaining_time":46.65819552},
{"learn":[0.01635337542],"iteration":263,"passed_time":16.73363146,"remaining_time":46.65133619},
{"learn":[0.01623888994],"iteration":264,"passed_time":16.80616362,"remaining_time":46.61332174},
{"learn":[0.01613549789],"iteration":265,"passed_time":16.89150453,"remaining_time":46.6103922},
{"learn":[0.01594919774],"iteration":266,"passed_time":16.97009087,"remaining_time":46.58830191},
{"learn":[0.01586584062],"iteration":267,"passed_time":17.04410612,"remaining_time":46.55330479},
{"learn":[0.01580371792],"iteration":268,"passed_time":17.15084584,"remaining_time":46.60694538},
{"learn":[0.01570454827],"iteration":269,"passed_time":17.26127837,"remaining_time":46.66938226},
{"learn":[0.01557758824],"iteration":270,"passed_time":17.33085294,"remaining_time":46.62063394},
{"learn":[0.01549521909],"iteration":271,"passed_time":17.3799035,"remaining_time":46.51680054},
{"learn":[0.01532393427],"iteration":272,"passed_time":17.4282923,"remaining_time":46.41160622},
{"learn":[0.01522766354],"iteration":273,"passed_time":17.47569004,"remaining_time":46.30420062},
{"learn":[0.01514100398],"iteration":274,"passed_time":17.52728132,"remaining_time":46.20828713},
{"learn":[0.01507334273],"iteration":275,"passed_time":17.57898707,"remaining_time":46.11299507},
{"learn":[0.01501883917],"iteration":276,"passed_time":17.62899808,"remaining_time":46.01359426},
{"learn":[0.01493573929],"iteration":277,"passed_time":17.67610003,"remaining_time":45.9069936},
{"learn":[0.01487039974],"iteration":278,"passed_time":17.72662624,"remaining_time":45.80966853},
{"learn":[0.01478175858],"iteration":279,"passed_time":17.76959794,"remaining_time":45.69325184},
{"learn":[0.01468853755],"iteration":280,"passed_time":17.82037272,"remaining_time":45.59732379},
{"learn":[0.01462436654],"iteration":281,"passed_time":17.87018013,"remaining_time":45.49925295},
{"learn":[0.01456549757],"iteration":282,"passed_time":17.9211206,"remaining_time":45.40439389},
{"learn":[0.01448608908],"iteration":283,"passed_time":17.97652745,"remaining_time":45.32110442},
{"learn":[0.0144201508],"iteration":284,"passed_time":18.03047167,"remaining_time":45.23434122},
{"learn":[0.01435653217],"iteration":285,"passed_time":18.08392082,"remaining_time":45.14657157},
{"learn":[0.01427031618],"iteration":286,"passed_time":18.13717732,"remaining_time":45.05856248},
{"learn":[0.01421696905],"iteration":287,"passed_time":18.18615638,"remaining_time":44.96021994},
{"learn":[0.01415984765],"iteration":288,"passed_time":18.23527651,"remaining_time":44.86256609},
{"learn":[0.01409538257],"iteration":289,"passed_time":18.2820446,"remaining_time":44.7594885},
{"learn":[0.01401723957],"iteration":290,"passed_time":18.3257133,"remaining_time":44.64924648},
{"learn":[0.01387788641],"iteration":291,"passed_time":18.37035528,"remaining_time":44.54182035},
{"learn":[0.01381318039],"iteration":292,"passed_time":18.42189578,"remaining_time":44.45146865},
{"learn":[0.0136992949],"iteration":293,"passed_time":18.46496761,"remaining_time":44.34104467},
{"learn":[0.01364623087],"iteration":294,"passed_time":18.51559327,"remaining_time":44.24912969},
{"learn":[0.013598967],"iteration":295,"passed_time":18.55785541,"remaining_time":44.13760204},
{"learn":[0.01354108837],"iteration":296,"passed_time":18.60697573,"remaining_time":44.04277419},
{"learn":[0.01347121748],"iteration":297,"passed_time":18.65671807,"remaining_time":43.94971842},
{"learn":[0.01343089809],"iteration":298,"passed_time":18.70388851,"remaining_time":43.85092257},
{"learn":[0.01338732867],"iteration":299,"passed_time":18.7490775,"remaining_time":43.74784749},
{"learn":[0.01332900245],"iteration":300,"passed_time":18.80103115,"remaining_time":43.66086637},
{"learn":[0.01325900372],"iteration":301,"passed_time":18.84743348,"remaining_time":43.56128666},
{"learn":[0.01318292764],"iteration":302,"passed_time":18.89217956,"remaining_time":43.45824803},
{"learn":[0.01310124674],"iteration":303,"passed_time":18.93769524,"remaining_time":43.3573549},
{"learn":[0.01305005488],"iteration":304,"passed_time":18.98377091,"remaining_time":43.25810092},
{"learn":[0.01297793637],"iteration":305,"passed_time":19.02881847,"remaining_time":43.15686281},
{"learn":[0.01291477301],"iteration":306,"passed_time":19.07409471,"remaining_time":43.05650695},
{"learn":[0.0128585017],"iteration":307,"passed_time":19.12659256,"remaining_time":42.97273394},
{"learn":[0.01280711937],"iteration":308,"passed_time":19.1733716,"remaining_time":42.87637468},
{"learn":[0.01273929332],"iteration":309,"passed_time":19.22350997,"remaining_time":42.78781251},
{"learn":[0.0126936946],"iteration":310,"passed_time":19.27195124,"remaining_time":42.69573764},
{"learn":[0.01264872253],"iteration":311,"passed_time":19.32245446,"remaining_time":42.60848932},
{"learn":[0.01260901535],"iteration":312,"passed_time":19.36930533,"remaining_time":42.51345929},
{"learn":[0.0125250168],"iteration":313,"passed_time":19.41444986,"remaining_time":42.41500829},
{"learn":[0.0124818982],"iteration":314,"passed_time":19.46690479,"remaining_time":42.33279296},
{"learn":[0.01243230095],"iteration":315,"passed_time":19.51801579,"remaining_time":42.24785697},
{"learn":[0.01237213456],"iteration":316,"passed_time":19.5672457,"remaining_time":42.15908143},
{"learn":[0.01232171482],"iteration":317,"passed_time":19.61916773,"remaining_time":42.07632827},
{"learn":[0.01226635922],"iteration":318,"passed_time":19.66698625,"remaining_time":41.98500825},
{"learn":[0.01221608159],"iteration":319,"passed_time":19.71889066,"remaining_time":41.90264265},
{"learn":[0.01214616893],"iteration":320,"passed_time":19.76506656,"remaining_time":41.80834951},
{"learn":[0.01206259644],"iteration":321,"passed_time":19.81512706,"remaining_time":41.72253462},
{"learn":[0.0120034008],"iteration":322,"passed_time":19.86244478,"remaining_time":41.63119232},
{"learn":[0.01194468748],"iteration":323,"passed_time":19.91542249,"remaining_time":41.55193087},
{"learn":[0.01189768384],"iteration":324,"passed_time":19.95814245,"remaining_time":41.45152662},
{"learn":[0.01184269175],"iteration":325,"passed_time":20.00668949,"remaining_time":41.36352366},
{"learn":[0.01179230581],"iteration":326,"passed_time":20.05845238,"remaining_time":41.28238058},
{"learn":[0.01175323735],"iteration":327,"passed_time":20.11025987,"remaining_time":41.20150803},
{"learn":[0.01169886702],"iteration":328,"passed_time":20.16090927,"remaining_time":41.11845021},
{"learn":[0.01164867286],"iteration":329,"passed_time":20.20945205,"remaining_time":41.03131173},
{"learn":[0.01159978153],"iteration":330,"passed_time":20.26469813,"remaining_time":40.95795484},
{"learn":[0.01156569196],"iteration":331,"passed_time":20.31691447,"remaining_time":40.87861105},
{"learn":[0.01152656233],"iteration":332,"passed_time":20.3672973,"remaining_time":40.79575766},
{"learn":[0.01146380207],"iteration":333,"passed_time":20.4239639,"remaining_time":40.72562862},
{"learn":[0.01141987181],"iteration":334,"passed_time":20.47720339,"remaining_time":40.64877688},
{"learn":[0.01136912142],"iteration":335,"passed_time":20.5301924,"remaining_time":40.5715707},
{"learn":[0.01132948308],"iteration":336,"passed_time":20.57731023,"remaining_time":40.48295751},
{"learn":[0.01128731361],"iteration":337,"passed_time":20.6322393,"remaining_time":40.40988881},
{"learn":[0.01123640786],"iteration":338,"passed_time":20.73399286,"remaining_time":40.42822797},
{"learn":[0.01120118953],"iteration":339,"passed_time":20.81270539,"remaining_time":40.401134},
{"learn":[0.01116396447],"iteration":340,"passed_time":20.87140871,"remaining_time":40.33506845},
{"learn":[0.01109833515],"iteration":341,"passed_time":20.94113959,"remaining_time":40.29026272},
{"learn":[0.01106604395],"iteration":342,"passed_time":21.00952403,"remaining_time":40.24273262},
{"learn":[0.01100655596],"iteration":343,"passed_time":21.06811898,"remaining_time":40.17641294},
{"learn":[0.01097156028],"iteration":344,"passed_time":21.12378835,"remaining_time":40.10458367},
{"learn":[0.01093739172],"iteration":345,"passed_time":21.18662587,"remaining_time":40.04639687},
{"learn":[0.01089876694],"iteration":346,"passed_time":21.2448888,"remaining_time":39.9795746},
{"learn":[0.01086535893],"iteration":347,"passed_time":21.30499326,"remaining_time":39.91625173},
{"learn":[0.01083650252],"iteration":348,"passed_time":21.37587769,"remaining_time":39.87305552},
{"learn":[0.01079966676],"iteration":349,"passed_time":21.44022875,"remaining_time":39.81756769},
{"learn":[0.01076039446],"iteration":350,"passed_time":21.50001269,"remaining_time":39.75358471},
{"learn":[0.0107027669],"iteration":351,"passed_time":21.56983185,"remaining_time":39.70809954},
{"learn":[0.01065099802],"iteration":352,"passed_time":21.6338726,"remaining_time":39.65188547},
{"learn":[0.01060897423],"iteration":353,"passed_time":21.69819772,"remaining_time":39.59614613},
{"learn":[0.01056323553],"iteration":354,"passed_time":21.77844072,"remaining_time":39.56927962},
{"learn":[0.01051998965],"iteration":355,"passed_time":21.84053274,"remaining_time":39.50927833},
{"learn":[0.01048244586],"iteration":356,"passed_time":21.90188819,"remaining_time":39.44793867},
{"learn":[0.01042231204],"iteration":357,"passed_time":21.97249109,"remaining_time":39.40318234},
{"learn":[0.01038494743],"iteration":358,"passed_time":22.03486974,"remaining_time":39.3435975},
{"learn":[0.01035739448],"iteration":359,"passed_time":22.08621094,"remaining_time":39.264375},
{"learn":[0.01029854322],"iteration":360,"passed_time":22.15262136,"remaining_time":39.21198075},
{"learn":[0.01022444685],"iteration":361,"passed_time":22.22647951,"remaining_time":39.17263515},
{"learn":[0.01018620042],"iteration":362,"passed_time":22.29996496,"remaining_time":39.13244539},
{"learn":[0.0101397675],"iteration":363,"passed_time":22.3530603,"remaining_time":39.05644602},
{"learn":[0.01007651754],"iteration":364,"passed_time":22.40248178,"remaining_time":38.97418063},
{"learn":[0.01003833545],"iteration":365,"passed_time":22.44957655,"remaining_time":38.8880643},
{"learn":[0.009969518866],"iteration":366,"passed_time":22.49797263,"remaining_time":38.80440511},
{"learn":[0.009906956728],"iteration":367,"passed_time":22.54763421,"remaining_time":38.72311092},
{"learn":[0.009878947574],"iteration":368,"passed_time":22.59783437,"remaining_time":38.64290918},
{"learn":[0.009852455895],"iteration":369,"passed_time":22.65157852,"remaining_time":38.56890397},
{"learn":[0.009818091521],"iteration":370,"passed_time":22.70221991,"remaining_time":38.48974749},
{"learn":[0.009787053203],"iteration":371,"passed_time":22.76591551,"remaining_time":38.43278209},
{"learn":[0.009765083129],"iteration":372,"passed_time":22.82093639,"remaining_time":38.3611987},
{"learn":[0.009733563678],"iteration":373,"passed_time":22.87375009,"remaining_time":38.28600951},
{"learn":[0.009706578244],"iteration":374,"passed_time":22.92992313,"remaining_time":38.21653856},
{"learn":[0.009666050922],"iteration":375,"passed_time":22.97828065,"remaining_time":38.13416789},
{"learn":[0.009608184722],"iteration":376,"passed_time":23.03305364,"remaining_time":38.06257936},
{"learn":[0.009553155707],"iteration":377,"passed_time":23.08585191,"remaining_time":37.9878304},
{"learn":[0.009529884867],"iteration":378,"passed_time":23.14686534,"remaining_time":37.92665799},
{"learn":[0.009507971119],"iteration":379,"passed_time":23.1988317,"remaining_time":37.8507254},
{"learn":[0.009464823104],"iteration":380,"passed_time":23.25409091,"remaining_time":37.78026843},
{"learn":[0.009434439097],"iteration":381,"passed_time":23.30566376,"remaining_time":37.70392723},
{"learn":[0.009398953037],"iteration":382,"passed_time":23.36274312,"remaining_time":37.63658618},
{"learn":[0.009369013415],"iteration":383,"passed_time":23.4143416,"remaining_time":37.56050632},
{"learn":[0.009350103421],"iteration":384,"passed_time":23.4650478,"remaining_time":37.4831283},
{"learn":[0.009320480085],"iteration":385,"passed_time":23.51244622,"remaining_time":37.4006269},
{"learn":[0.009288936631],"iteration":386,"passed_time":23.56467313,"remaining_time":37.32595512},
{"learn":[0.009257037439],"iteration":387,"passed_time":23.6137504,"remaining_time":37.24643105},
{"learn":[0.009219800876],"iteration":388,"passed_time":23.67275762,"remaining_time":37.18266043},
{"learn":[0.009199737229],"iteration":389,"passed_time":23.73052396,"remaining_time":37.11697337},
{"learn":[0.009161406169],"iteration":390,"passed_time":23.77546696,"remaining_time":37.03135391},
{"learn":[0.009135943369],"iteration":391,"passed_time":23.82775707,"remaining_time":36.9573375},
{"learn":[0.009115846024],"iteration":392,"passed_time":23.87771795,"remaining_time":36.87983408},
{"learn":[0.009067159814],"iteration":393,"passed_time":23.92556244,"remaining_time":36.79921532},
{"learn":[0.00904360632],"iteration":394,"passed_time":23.98184962,"remaining_time":36.73169373},
{"learn":[0.009014079376],"iteration":395,"passed_time":24.04947946,"remaining_time":36.68152927},
{"learn":[0.008973711859],"iteration":396,"passed_time":24.0990515,"remaining_time":36.603849},
{"learn":[0.008936448051],"iteration":397,"passed_time":24.15110392,"remaining_time":36.5300617},
{"learn":[0.008907823771],"iteration":398,"passed_time":24.19847531,"remaining_time":36.44933248},
{"learn":[0.008874680843],"iteration":399,"passed_time":24.24648687,"remaining_time":36.36973031},
{"learn":[0.008852327404],"iteration":400,"passed_time":24.29018839,"remaining_time":36.28384749},
{"learn":[0.008826130421],"iteration":401,"passed_time":24.34424649,"remaining_time":36.2135806},
{"learn":[0.008788430776],"iteration":402,"passed_time":24.39743398,"remaining_time":36.14210443},
{"learn":[0.008762161973],"iteration":403,"passed_time":24.45072941,"remaining_time":36.07087804},
{"learn":[0.008745046306],"iteration":404,"passed_time":24.50751731,"remaining_time":36.0048711},
{"learn":[0.008695765008],"iteration":405,"passed_time":24.56149327,"remaining_time":35.93479558},
{"learn":[0.008669589575],"iteration":406,"passed_time":24.61732908,"remaining_time":35.86750896},
{"learn":[0.008644376607],"iteration":407,"passed_time":24.68064559,"remaining_time":35.81113282},
{"learn":[0.00860023384],"iteration":408,"passed_time":24.73182151,"remaining_time":35.73717974},
{"learn":[0.008578477754],"iteration":409,"passed_time":24.79428885,"remaining_time":35.67958639},
{"learn":[0.008557660979],"iteration":410,"passed_time":24.84781631,"remaining_time":35.60915769},
{"learn":[0.00853171338],"iteration":411,"passed_time":24.90624509,"remaining_time":35.5458061},
{"learn":[0.008489580779],"iteration":412,"passed_time":24.96125268,"remaining_time":35.47761579},
{"learn":[0.008469004416],"iteration":413,"passed_time":25.01667192,"remaining_time":35.41007185},
{"learn":[0.008445160199],"iteration":414,"passed_time":25.07825414,"remaining_time":35.35127391},
{"learn":[0.008427768642],"iteration":415,"passed_time":25.13513628,"remaining_time":35.2858644},
{"learn":[0.008395632539],"iteration":416,"passed_time":25.20418539,"remaining_time":35.23750619},
{"learn":[0.008375187408],"iteration":417,"passed_time":25.28160454,"remaining_time":35.20070297},
{"learn":[0.008360082154],"iteration":418,"passed_time":25.34311106,"remaining_time":35.14164088},
{"learn":[0.008335501373],"iteration":419,"passed_time":25.39692577,"remaining_time":35.07194512},
{"learn":[0.008316010379],"iteration":420,"passed_time":25.49829411,"remaining_time":35.06772515},
{"learn":[0.008290098525],"iteration":421,"passed_time":25.56016374,"remaining_time":35.00894464},
{"learn":[0.008265768639],"iteration":422,"passed_time":25.64694598,"remaining_time":34.98413198},
{"learn":[0.008245474566],"iteration":423,"passed_time":25.71131761,"remaining_time":34.92858241},
{"learn":[0.008217536109],"iteration":424,"passed_time":25.78724815,"remaining_time":34.88862985},
{"learn":[0.008193486299],"iteration":425,"passed_time":25.84699517,"remaining_time":34.82670242},
{"learn":[0.008161319314],"iteration":426,"passed_time":25.89579532,"remaining_time":34.75009536},
{"learn":[0.008139651264],"iteration":427,"passed_time":25.94608709,"remaining_time":34.67561172},
{"learn":[0.008116065701],"iteration":428,"passed_time":26.00650993,"remaining_time":34.61472534},
{"learn":[0.008092704201],"iteration":429,"passed_time":26.06727169,"remaining_time":34.55429038},
{"learn":[0.008049135243],"iteration":430,"passed_time":26.11976241,"remaining_time":34.48293459},
{"learn":[0.008028960575],"iteration":431,"passed_time":26.17743501,"remaining_time":34.41847936},
{"learn":[0.008008269934],"iteration":432,"passed_time":26.22282334,"remaining_time":34.33796959},
{"learn":[0.007990636488],"iteration":433,"passed_time":26.27231316,"remaining_time":34.26297062},
{"learn":[0.00796793558],"iteration":434,"passed_time":26.31743385,"remaining_time":34.18241408},
{"learn":[0.007949683035],"iteration":435,"passed_time":26.36680282,"remaining_time":34.10751558},
{"learn":[0.007934207083],"iteration":436,"passed_time":26.41799674,"remaining_time":34.03508504},
{"learn":[0.007897738214],"iteration":437,"passed_time":26.46837762,"remaining_time":33.96170827},
{"learn":[0.007872830399],"iteration":438,"passed_time":26.51778464,"remaining_time":33.88719176},
{"learn":[0.007854596828],"iteration":439,"passed_time":26.5675131,"remaining_time":33.81319849},
{"learn":[0.007835487971],"iteration":440,"passed_time":26.61435437,"remaining_time":33.73565554},
{"learn":[0.007821148358],"iteration":441,"passed_time":26.66199255,"remaining_time":33.65925757},
{"learn":[0.007790009139],"iteration":442,"passed_time":26.71784525,"remaining_time":33.59331784},
{"learn":[0.007768802936],"iteration":443,"passed_time":26.76724608,"remaining_time":33.51934419},
{"learn":[0.007749927305],"iteration":444,"passed_time":26.81836003,"remaining_time":33.44761757},
{"learn":[0.007736082075],"iteration":445,"passed_time":26.87018737,"remaining_time":33.37686951},
{"learn":[0.007715744998],"iteration":446,"passed_time":26.91769889,"remaining_time":33.30086687},
{"learn":[0.007676919909],"iteration":447,"passed_time":26.98111237,"remaining_time":33.24458489},
{"learn":[0.00766170396],"iteration":448,"passed_time":27.03679236,"remaining_time":33.17878082},
{"learn":[0.007640043881],"iteration":449,"passed_time":27.09102536,"remaining_time":33.11125322},
{"learn":[0.007619175188],"iteration":450,"passed_time":27.14273038,"remaining_time":33.04070727},
{"learn":[0.007600363067],"iteration":451,"passed_time":27.20568429,"remaining_time":32.98388272},
{"learn":[0.007569090866],"iteration":452,"passed_time":27.27112565,"remaining_time":32.93003473},
{"learn":[0.007544417799],"iteration":453,"passed_time":27.32690761,"remaining_time":32.86451885},
{"learn":[0.007516668053],"iteration":454,"passed_time":27.39016579,"remaining_time":32.80800078},
{"learn":[0.007499166994],"iteration":455,"passed_time":27.45618061,"remaining_time":32.75474178},
{"learn":[0.007483999665],"iteration":456,"passed_time":27.52138421,"remaining_time":32.70046308},
{"learn":[0.007467185351],"iteration":457,"passed_time":27.58661054,"remaining_time":32.64616356},
{"learn":[0.00745103557],"iteration":458,"passed_time":27.6553753,"remaining_time":32.59598701},
{"learn":[0.007423908828],"iteration":459,"passed_time":27.71524282,"remaining_time":32.53528505},
{"learn":[0.007393983939],"iteration":460,"passed_time":27.76762151,"remaining_time":32.46583079},
{"learn":[0.007373738864],"iteration":461,"passed_time":27.81420587,"remaining_time":32.38970294},
{"learn":[0.007338468294],"iteration":462,"passed_time":27.87243145,"remaining_time":32.32720451},
{"learn":[0.007317522813],"iteration":463,"passed_time":27.9282014,"remaining_time":32.26188783},
{"learn":[0.007294939481],"iteration":464,"passed_time":27.98897053,"remaining_time":32.20236395},
{"learn":[0.007274633889],"iteration":465,"passed_time":28.04204936,"remaining_time":32.13402223},
{"learn":[0.007258415876],"iteration":466,"passed_time":28.09352461,"remaining_time":32.06391566},
{"learn":[0.00722679619],"iteration":467,"passed_time":28.13738019,"remaining_time":31.98522705},
{"learn":[0.007201178657],"iteration":468,"passed_time":28.18418707,"remaining_time":31.91002843},
{"learn":[0.007184187726],"iteration":469,"passed_time":28.23176196,"remaining_time":31.83581668},
{"learn":[0.007168726382],"iteration":470,"passed_time":28.28209138,"remaining_time":31.76481176},
{"learn":[0.007144133669],"iteration":471,"passed_time":28.34801374,"remaining_time":31.7113374},
{"learn":[0.007122813533],"iteration":472,"passed_time":28.41832768,"remaining_time":31.66270335},
{"learn":[0.007102865659],"iteration":473,"passed_time":28.48581461,"remaining_time":31.61084069},
{"learn":[0.007070972184],"iteration":474,"passed_time":28.54517053,"remaining_time":31.54992532},
{"learn":[0.007052775704],"iteration":475,"passed_time":28.59641446,"remaining_time":31.4800865},
{"learn":[0.007032878034],"iteration":476,"passed_time":28.645447,"remaining_time":31.407901},
{"learn":[0.007020734376],"iteration":477,"passed_time":28.69917172,"remaining_time":31.34093648},
{"learn":[0.007007486133],"iteration":478,"passed_time":28.76643136,"remaining_time":31.28874893},
{"learn":[0.00699482509],"iteration":479,"passed_time":28.82772449,"remaining_time":31.23003486},
{"learn":[0.00697574601],"iteration":480,"passed_time":28.88195606,"remaining_time":31.16369064},
{"learn":[0.006957745724],"iteration":481,"passed_time":28.92979958,"remaining_time":31.0905315},
{"learn":[0.006938422388],"iteration":482,"passed_time":28.98726791,"remaining_time":31.02777952},
{"learn":[0.006924060148],"iteration":483,"passed_time":29.03324545,"remaining_time":30.95279887},
{"learn":[0.006903425271],"iteration":484,"passed_time":29.084327,"remaining_time":30.88335754},
{"learn":[0.006886007583],"iteration":485,"passed_time":29.13718294,"remaining_time":30.81586838},
{"learn":[0.006870157977],"iteration":486,"passed_time":29.18908661,"remaining_time":30.7474362},
{"learn":[0.00685548955],"iteration":487,"passed_time":29.24242118,"remaining_time":30.68057304},
{"learn":[0.006834770247],"iteration":488,"passed_time":29.28896812,"remaining_time":30.6066722},
{"learn":[0.006816304063],"iteration":489,"passed_time":29.3389,"remaining_time":30.53640612},
{"learn":[0.006803242222],"iteration":490,"passed_time":29.39062516,"remaining_time":30.46808189},
{"learn":[0.006792298562],"iteration":491,"passed_time":29.43470427,"remaining_time":30.39193042},
{"learn":[0.006773276212],"iteration":492,"passed_time":29.48052966,"remaining_time":30.31770495},
{"learn":[0.006751955166],"iteration":493,"passed_time":29.52696695,"remaining_time":30.2442212},
{"learn":[0.006738936241],"iteration":494,"passed_time":29.57563286,"remaining_time":30.1731204},
{"learn":[0.006728129378],"iteration":495,"passed_time":29.62427554,"remaining_time":30.10208644},
{"learn":[0.006714127439],"iteration":496,"passed_time":29.66871086,"remaining_time":30.02688443},
{"learn":[0.006704499749],"iteration":497,"passed_time":29.71811402,"remaining_time":29.95681373},
{"learn":[0.006693977884],"iteration":498,"passed_time":29.76942534,"remaining_time":29.88874167},
{"learn":[0.006677518361],"iteration":499,"passed_time":29.81730554,"remaining_time":29.81730554},
{"learn":[0.006667108276],"iteration":500,"passed_time":29.86372593,"remaining_time":29.74450946},
{"learn":[0.006657046246],"iteration":501,"passed_time":29.91876339,"remaining_time":29.68036687},
{"learn":[0.006641947449],"iteration":502,"passed_time":29.97239112,"remaining_time":29.61486757},
{"learn":[0.006630304524],"iteration":503,"passed_time":30.0243509,"remaining_time":29.5477739},
{"learn":[0.006617745495],"iteration":504,"passed_time":30.09376486,"remaining_time":29.49784872},
{"learn":[0.006605965565],"iteration":505,"passed_time":30.14817754,"remaining_time":29.433201},
{"learn":[0.006589852631],"iteration":506,"passed_time":30.19389296,"remaining_time":29.36013654},
{"learn":[0.006567181865],"iteration":507,"passed_time":30.24848983,"remaining_time":29.29578149},
{"learn":[0.006555002353],"iteration":508,"passed_time":30.2994877,"remaining_time":29.22799305},
{"learn":[0.006535202267],"iteration":509,"passed_time":30.33972824,"remaining_time":29.14993498},
{"learn":[0.00652384453],"iteration":510,"passed_time":30.39016584,"remaining_time":29.08178296},
{"learn":[0.006511743838],"iteration":511,"passed_time":30.43750055,"remaining_time":29.01074271},
{"learn":[0.00650204363],"iteration":512,"passed_time":30.49089567,"remaining_time":28.94554813},
{"learn":[0.006488071914],"iteration":513,"passed_time":30.53631936,"remaining_time":28.87286228},
{"learn":[0.006476617212],"iteration":514,"passed_time":30.58341618,"remaining_time":28.80185796},
{"learn":[0.006460543577],"iteration":515,"passed_time":30.62978136,"remaining_time":28.73026003},
{"learn":[0.006449638884],"iteration":516,"passed_time":30.67346774,"remaining_time":28.65625709},
{"learn":[0.006432652048],"iteration":517,"passed_time":30.73632296,"remaining_time":28.60020786},
{"learn":[0.006418241543],"iteration":518,"passed_time":30.79844328,"remaining_time":28.54345128},
{"learn":[0.006410002657],"iteration":519,"passed_time":30.85162047,"remaining_time":28.4784189},
{"learn":[0.006396203095],"iteration":520,"passed_time":30.90122381,"remaining_time":28.41014626},
{"learn":[0.006384281033],"iteration":521,"passed_time":30.94346814,"remaining_time":28.33520646},
{"learn":[0.006372524934],"iteration":522,"passed_time":31.0004176,"remaining_time":28.27380344},
{"learn":[0.006358331333],"iteration":523,"passed_time":31.04834396,"remaining_time":28.20422085},
{"learn":[0.006332752676],"iteration":524,"passed_time":31.08895302,"remaining_time":28.12810035},
{"learn":[0.0063210229],"iteration":525,"passed_time":31.13485708,"remaining_time":28.05688641},
{"learn":[0.006308433476],"iteration":526,"passed_time":31.18525802,"remaining_time":27.98980464},
{"learn":[0.006292983822],"iteration":527,"passed_time":31.23223459,"remaining_time":27.91972486},
{"learn":[0.006277002506],"iteration":528,"passed_time":31.2741851,"remaining_time":27.84525743},
{"learn":[0.006264732446],"iteration":529,"passed_time":31.31894823,"remaining_time":27.77340692},
{"learn":[0.006239648733],"iteration":530,"passed_time":31.36489191,"remaining_time":27.70270114},
{"learn":[0.006222278451],"iteration":531,"passed_time":31.41183237,"remaining_time":27.63296532},
{"learn":[0.006200971834],"iteration":532,"passed_time":31.4532221,"remaining_time":27.55845163},
{"learn":[0.006185614821],"iteration":533,"passed_time":31.50522419,"remaining_time":27.49332299},
{"learn":[0.006171845563],"iteration":534,"passed_time":31.55127629,"remaining_time":27.42307192},
{"learn":[0.006141326043],"iteration":535,"passed_time":31.60177445,"remaining_time":27.35675997},
{"learn":[0.006128463893],"iteration":536,"passed_time":31.64689687,"remaining_time":27.28587197},
{"learn":[0.006104600197],"iteration":537,"passed_time":31.69351582,"remaining_time":27.21636489},
{"learn":[0.006085928443],"iteration":538,"passed_time":31.73731995,"remaining_time":27.14453524},
{"learn":[0.006070928149],"iteration":539,"passed_time":31.79846694,"remaining_time":27.08758295},
{"learn":[0.006058597098],"iteration":540,"passed_time":31.84627011,"remaining_time":27.01929386},
{"learn":[0.006049327898],"iteration":541,"passed_time":31.91730699,"remaining_time":26.97071328},
{"learn":[0.006037146394],"iteration":542,"passed_time":31.96995047,"remaining_time":26.90656973},
{"learn":[0.006023666346],"iteration":543,"passed_time":32.02204232,"remaining_time":26.84200606},
{"learn":[0.006011004166],"iteration":544,"passed_time":32.06574054,"remaining_time":26.77048064},
{"learn":[0.006003422958],"iteration":545,"passed_time":32.11391267,"remaining_time":26.7027772},
{"learn":[0.005989721845],"iteration":546,"passed_time":32.1622949,"remaining_time":26.63531918},
{"learn":[0.005978509182],"iteration":547,"passed_time":32.2066304,"remaining_time":26.56459296},
{"learn":[0.005966312319],"iteration":548,"passed_time":32.26023309,"remaining_time":26.50157582},
{"learn":[0.005947439813],"iteration":549,"passed_time":32.31405136,"remaining_time":26.43876929},
{"learn":[0.005933160232],"iteration":550,"passed_time":32.36308774,"remaining_time":26.37209872},
{"learn":[0.005904540716],"iteration":551,"passed_time":32.41521185,"remaining_time":26.30799802},
{"learn":[0.005882730411],"iteration":552,"passed_time":32.46056207,"remaining_time":26.23846518},
{"learn":[0.005870178135],"iteration":553,"passed_time":32.51086023,"remaining_time":26.173003},
{"learn":[0.005860085685],"iteration":554,"passed_time":32.5567671,"remaining_time":26.10407452},
{"learn":[0.005849673421],"iteration":555,"passed_time":32.6129011,"remaining_time":26.04339585},
{"learn":[0.005835123788],"iteration":556,"passed_time":32.66116194,"remaining_time":25.9764717},
{"learn":[0.005824499064],"iteration":557,"passed_time":32.70994529,"remaining_time":25.91002835},
{"learn":[0.005811191136],"iteration":558,"passed_time":32.75762942,"remaining_time":25.84278099},
{"learn":[0.005802568051],"iteration":559,"passed_time":32.81082794,"remaining_time":25.77993624},
{"learn":[0.005793246262],"iteration":560,"passed_time":32.8598635,"remaining_time":25.71386823},
{"learn":[0.005783784967],"iteration":561,"passed_time":32.91094019,"remaining_time":25.64945161},
{"learn":[0.005769268548],"iteration":562,"passed_time":32.95943471,"remaining_time":25.5830781},
{"learn":[0.005754527015],"iteration":563,"passed_time":33.00961691,"remaining_time":25.51807265},
{"learn":[0.005744850978],"iteration":564,"passed_time":33.06278781,"remaining_time":25.4554207},
{"learn":[0.005738035038],"iteration":565,"passed_time":33.12051463,"remaining_time":25.39629567},
{"learn":[0.005723148174],"iteration":566,"passed_time":33.17860567,"remaining_time":25.33745371},
{"learn":[0.005710771267],"iteration":567,"passed_time":33.22907919,"remaining_time":25.27282079},
{"learn":[0.005691264849],"iteration":568,"passed_time":33.28723765,"remaining_time":25.21405875},
{"learn":[0.005676823456],"iteration":569,"passed_time":33.35659166,"remaining_time":25.16374458},
{"learn":[0.00566274527],"iteration":570,"passed_time":33.41067713,"remaining_time":25.10189228},
{"learn":[0.005644623801],"iteration":571,"passed_time":33.45641308,"remaining_time":25.03381958},
{"learn":[0.005636649964],"iteration":572,"passed_time":33.49907837,"remaining_time":24.96353659},
{"learn":[0.005616772734],"iteration":573,"passed_time":33.54454122,"remaining_time":24.89542606},
{"learn":[0.005606427245],"iteration":574,"passed_time":33.59297453,"remaining_time":24.82958987},
{"learn":[0.005594008484],"iteration":575,"passed_time":33.63982423,"remaining_time":24.76264839},
{"learn":[0.005582573925],"iteration":576,"passed_time":33.67949483,"remaining_time":24.69051354},
{"learn":[0.005572462275],"iteration":577,"passed_time":33.73139236,"remaining_time":24.62741795},
{"learn":[0.005552148984],"iteration":578,"passed_time":33.77824138,"remaining_time":24.56069019},
{"learn":[0.005544824383],"iteration":579,"passed_time":33.84214677,"remaining_time":24.50638214},
{"learn":[0.00553301151],"iteration":580,"passed_time":33.89269972,"remaining_time":24.44241168},
{"learn":[0.005523293596],"iteration":581,"passed_time":33.94422625,"remaining_time":24.37918655},
{"learn":[0.005517042502],"iteration":582,"passed_time":33.99137847,"remaining_time":24.31287276},
{"learn":[0.005502661124],"iteration":583,"passed_time":34.03980859,"remaining_time":24.24753489},
{"learn":[0.005489294984],"iteration":584,"passed_time":34.08138648,"remaining_time":24.17739383},
{"learn":[0.005467644116],"iteration":585,"passed_time":34.12983912,"remaining_time":24.11220716},
{"learn":[0.005461519828],"iteration":586,"passed_time":34.18385474,"remaining_time":24.0509915},
{"learn":[0.005453973409],"iteration":587,"passed_time":34.23832105,"remaining_time":23.99011611},
{"learn":[0.005440548966],"iteration":588,"passed_time":34.29524679,"remaining_time":23.93097866},
{"learn":[0.005426391103],"iteration":589,"passed_time":34.35929275,"remaining_time":23.87679666},
{"learn":[0.005411958939],"iteration":590,"passed_time":34.40680032,"remaining_time":23.81113592},
{"learn":[0.005394593974],"iteration":591,"passed_time":34.45127,"remaining_time":23.74344284},
{"learn":[0.00537805905],"iteration":592,"passed_time":34.50165156,"remaining_time":23.67988564},
{"learn":[0.005369135375],"iteration":593,"passed_time":34.54524904,"remaining_time":23.61173587},
{"learn":[0.005360316292],"iteration":594,"passed_time":34.58890925,"remaining_time":23.54371134},
{"learn":[0.005353723233],"iteration":595,"passed_time":34.63984864,"remaining_time":23.48070277},
{"learn":[0.005344826515],"iteration":596,"passed_time":34.69116408,"remaining_time":23.41798848},
{"learn":[0.005336605396],"iteration":597,"passed_time":34.75005781,"remaining_time":23.36040676},
{"learn":[0.005325527779],"iteration":598,"passed_time":34.80451372,"remaining_time":23.29984975},
{"learn":[0.005315956263],"iteration":599,"passed_time":34.85280457,"remaining_time":23.23520305},
{"learn":[0.005300125648],"iteration":600,"passed_time":34.8997278,"remaining_time":23.16970282},
{"learn":[0.005291713929],"iteration":601,"passed_time":34.94967662,"remaining_time":23.10626461},
{"learn":[0.005281234854],"iteration":602,"passed_time":35.00135693,"remaining_time":23.04401111},
{"learn":[0.005268868582],"iteration":603,"passed_time":35.04880723,"remaining_time":22.97901931},
{"learn":[0.0052580151],"iteration":604,"passed_time":35.09533477,"remaining_time":22.91348303},
{"learn":[0.005238178917],"iteration":605,"passed_time":35.14352791,"remaining_time":22.84909241},
{"learn":[0.00522842525],"iteration":606,"passed_time":35.18877307,"remaining_time":22.78284648},
{"learn":[0.005220117903],"iteration":607,"passed_time":35.24250433,"remaining_time":22.72214095},
{"learn":[0.005213232972],"iteration":608,"passed_time":35.28455413,"remaining_time":22.6539584},
{"learn":[0.005206355167],"iteration":609,"passed_time":35.33434326,"remaining_time":22.59080963},
{"learn":[0.005190469715],"iteration":610,"passed_time":35.38199441,"remaining_time":22.52634341},
{"learn":[0.005181836168],"iteration":611,"passed_time":35.43341266,"remaining_time":22.46432044},
{"learn":[0.005172686712],"iteration":612,"passed_time":35.4819625,"remaining_time":22.40052119},
{"learn":[0.005166305453],"iteration":613,"passed_time":35.52870537,"remaining_time":22.33563562},
{"learn":[0.005157808205],"iteration":614,"passed_time":35.57917217,"remaining_time":22.2731403},
{"learn":[0.005145451207],"iteration":615,"passed_time":35.63243201,"remaining_time":22.21242515},
{"learn":[0.005140047853],"iteration":616,"passed_time":35.68298778,"remaining_time":22.15005563},
{"learn":[0.005123966423],"iteration":617,"passed_time":35.7410961,"remaining_time":22.09239274},
{"learn":[0.005115467779],"iteration":618,"passed_time":35.79045305,"remaining_time":22.02934186},
{"learn":[0.005104280608],"iteration":619,"passed_time":35.85548625,"remaining_time":21.97594319},
{"learn":[0.00509583422],"iteration":620,"passed_time":35.9092874,"remaining_time":21.91565205},
{"learn":[0.00507683588],"iteration":621,"passed_time":35.95914776,"remaining_time":21.8529869},
{"learn":[0.005064571735],"iteration":622,"passed_time":36.0113652,"remaining_time":21.79178921},
{"learn":[0.005049438832],"iteration":623,"passed_time":36.06175533,"remaining_time":21.72951924},
{"learn":[0.005039130342],"iteration":624,"passed_time":36.11146733,"remaining_time":21.6668804},
{"learn":[0.00502604804],"iteration":625,"passed_time":36.16177481,"remaining_time":21.60463862},
{"learn":[0.005006506575],"iteration":626,"passed_time":36.207506,"remaining_time":21.5397125},
{"learn":[0.004996311333],"iteration":627,"passed_time":36.26127467,"remaining_time":21.47960856},
{"learn":[0.004985665374],"iteration":628,"passed_time":36.32421483,"remaining_time":21.42493434},
{"learn":[0.004976871125],"iteration":629,"passed_time":36.37155394,"remaining_time":21.36107136},
{"learn":[0.004964007893],"iteration":630,"passed_time":36.4132924,"remaining_time":21.29398557},
{"learn":[0.004950918751],"iteration":631,"passed_time":36.46027694,"remaining_time":21.23003467},
{"learn":[0.0049425624],"iteration":632,"passed_time":36.50807921,"remaining_time":21.16661149},
{"learn":[0.004935424991],"iteration":633,"passed_time":36.55771719,"remaining_time":21.10429731},
{"learn":[0.004924237744],"iteration":634,"passed_time":36.60808883,"remaining_time":21.04244476},
{"learn":[0.004913254248],"iteration":635,"passed_time":36.65466895,"remaining_time":20.97845833},
{"learn":[0.004905765163],"iteration":636,"passed_time":36.70337881,"remaining_time":20.9157402},
{"learn":[0.004898116171],"iteration":637,"passed_time":36.75017805,"remaining_time":20.8519819},
{"learn":[0.004886915305],"iteration":638,"passed_time":36.79694752,"remaining_time":20.78825987},
{"learn":[0.004880350679],"iteration":639,"passed_time":36.84299541,"remaining_time":20.72418492},
{"learn":[0.004868651459],"iteration":640,"passed_time":36.89230318,"remaining_time":20.66199195},
{"learn":[0.004860386206],"iteration":641,"passed_time":36.93669023,"remaining_time":20.59709518},
{"learn":[0.004852668359],"iteration":642,"passed_time":36.98682875,"remaining_time":20.53545546},
{"learn":[0.004844977525],"iteration":643,"passed_time":37.05326738,"remaining_time":20.48286209},
{"learn":[0.004834300511],"iteration":644,"passed_time":37.10800155,"remaining_time":20.4237838},
{"learn":[0.004826406333],"iteration":645,"passed_time":37.16705328,"remaining_time":20.36708492},
{"learn":[0.004815509709],"iteration":646,"passed_time":37.22482855,"remaining_time":20.30968235},
{"learn":[0.004809070712],"iteration":647,"passed_time":37.2764804,"remaining_time":20.24895232},
{"learn":[0.004802762399],"iteration":648,"passed_time":37.32506819,"remaining_time":20.18659312},
{"learn":[0.004795148137],"iteration":649,"passed_time":37.37304815,"remaining_time":20.12394901},
{"learn":[0.004787451114],"iteration":650,"passed_time":37.42093548,"remaining_time":20.06130028},
{"learn":[0.004776571509],"iteration":651,"passed_time":37.4709967,"remaining_time":19.99985714},
{"learn":[0.004771196468],"iteration":652,"passed_time":37.52023577,"remaining_time":19.93801196},
{"learn":[0.004764483965],"iteration":653,"passed_time":37.5619482,"remaining_time":19.87222336},
{"learn":[0.004756749408],"iteration":654,"passed_time":37.60724072,"remaining_time":19.80839396},
{"learn":[0.004746499733],"iteration":655,"passed_time":37.66841035,"remaining_time":19.75294689},
{"learn":[0.004736399742],"iteration":656,"passed_time":37.72004648,"remaining_time":19.69250524},
{"learn":[0.004728023042],"iteration":657,"passed_time":37.76902713,"remaining_time":19.63071015},
{"learn":[0.004710911654],"iteration":658,"passed_time":37.81968344,"remaining_time":19.56982102},
{"learn":[0.004704090203],"iteration":659,"passed_time":37.87068961,"remaining_time":19.50914313},
{"learn":[0.004690057562],"iteration":660,"passed_time":37.93069067,"remaining_time":19.45310762},
{"learn":[0.004684316266],"iteration":661,"passed_time":38.042306,"remaining_time":19.42341303},
{"learn":[0.004675422331],"iteration":662,"passed_time":38.10769415,"remaining_time":19.36997425},
{"learn":[0.0046696288],"iteration":663,"passed_time":38.17394988,"remaining_time":19.31693849},
{"learn":[0.004662743506],"iteration":664,"passed_time":38.22375169,"remaining_time":19.25557416},
{"learn":[0.004656357415],"iteration":665,"passed_time":38.28206544,"remaining_time":19.1985133},
{"learn":[0.004649850903],"iteration":666,"passed_time":38.3407587,"remaining_time":19.14163815},
{"learn":[0.004642830995],"iteration":667,"passed_time":38.40694246,"remaining_time":19.08848039},
{"learn":[0.004637396348],"iteration":668,"passed_time":38.53600227,"remaining_time":19.06639275},
{"learn":[0.004632721474],"iteration":669,"passed_time":38.65391378,"remaining_time":19.03849485},
{"learn":[0.004625847651],"iteration":670,"passed_time":38.78605127,"remaining_time":19.01730383},
{"learn":[0.00461321794],"iteration":671,"passed_time":38.84731999,"remaining_time":18.9611919},
{"learn":[0.004605909368],"iteration":672,"passed_time":38.9035985,"remaining_time":18.90263999},
{"learn":[0.00459843183],"iteration":673,"passed_time":38.95836588,"remaining_time":18.84336391},
{"learn":[0.004591026733],"iteration":674,"passed_time":39.01137464,"remaining_time":18.78325446},
{"learn":[0.004583499768],"iteration":675,"passed_time":39.06951302,"remaining_time":18.72562458},
{"learn":[0.004576572011],"iteration":676,"passed_time":39.12441342,"remaining_time":18.66644835},
{"learn":[0.004570271992],"iteration":677,"passed_time":39.18124526,"remaining_time":18.60820203},
{"learn":[0.004564346439],"iteration":678,"passed_time":39.23310722,"remaining_time":18.54761034},
{"learn":[0.004557353008],"iteration":679,"passed_time":39.28910348,"remaining_time":18.48898987},
{"learn":[0.004545504001],"iteration":680,"passed_time":39.33503203,"remaining_time":18.42566111},
{"learn":[0.004538875892],"iteration":681,"passed_time":39.39337844,"remaining_time":18.36817352},
{"learn":[0.004525245036],"iteration":682,"passed_time":39.45703201,"remaining_time":18.31314663},
{"learn":[0.004519021273],"iteration":683,"passed_time":39.50931693,"remaining_time":18.25284232},
{"learn":[0.004509123995],"iteration":684,"passed_time":39.56524747,"remaining_time":18.19423789},
{"learn":[0.004502900955],"iteration":685,"passed_time":39.62417629,"remaining_time":18.13701364},
{"learn":[0.004492546858],"iteration":686,"passed_time":39.68395432,"remaining_time":18.08017133},
{"learn":[0.004486203923],"iteration":687,"passed_time":39.74682718,"remaining_time":18.02472395},
{"learn":[0.00447618646],"iteration":688,"passed_time":39.79798736,"remaining_time":17.96396817},
{"learn":[0.004471300874],"iteration":689,"passed_time":39.8482587,"remaining_time":17.90284087},
{"learn":[0.004466246354],"iteration":690,"passed_time":39.90648873,"remaining_time":17.84530393},
{"learn":[0.004460042129],"iteration":691,"passed_time":39.95598742,"remaining_time":17.78387879},
{"learn":[0.004453760113],"iteration":692,"passed_time":40.00380833,"remaining_time":17.72174482},
{"learn":[0.00444777966],"iteration":693,"passed_time":40.05228146,"remaining_time":17.65993966},
{"learn":[0.004440799412],"iteration":694,"passed_time":40.10340043,"remaining_time":17.599334},
{"learn":[0.004436065622],"iteration":695,"passed_time":40.1551098,"remaining_time":17.53901348},
{"learn":[0.004430188211],"iteration":696,"passed_time":40.2165325,"remaining_time":17.48294024},
{"learn":[0.004423999923],"iteration":697,"passed_time":40.27051684,"remaining_time":17.42363336},
{"learn":[0.004417400625],"iteration":698,"passed_time":40.31933663,"remaining_time":17.36211777},
{"learn":[0.004411843522],"iteration":699,"passed_time":40.36941133,"remaining_time":17.30117629},
{"learn":[0.004407243145],"iteration":700,"passed_time":40.41801008,"remaining_time":17.23963625},
{"learn":[0.004397688214],"iteration":701,"passed_time":40.46889869,"remaining_time":17.17910514},
{"learn":[0.004384280579],"iteration":702,"passed_time":40.51943939,"remaining_time":17.11845448},
{"learn":[0.004379429425],"iteration":703,"passed_time":40.56722511,"remaining_time":17.05667419},
{"learn":[0.004373513838],"iteration":704,"passed_time":40.61837678,"remaining_time":16.99634206},
{"learn":[0.004369327149],"iteration":705,"passed_time":40.67179457,"remaining_time":16.93697961},
{"learn":[0.004361133559],"iteration":706,"passed_time":40.73906007,"remaining_time":16.88337284},
{"learn":[0.004355499939],"iteration":707,"passed_time":40.7942385,"remaining_time":16.82474243},
{"learn":[0.004350429403],"iteration":708,"passed_time":40.85177853,"remaining_time":16.76709105},
{"learn":[0.004339757957],"iteration":709,"passed_time":40.9089883,"remaining_time":16.70930508},
{"learn":[0.004335263016],"iteration":710,"passed_time":40.97649995,"remaining_time":16.65570814},
{"learn":[0.004328768552],"iteration":711,"passed_time":41.03401321,"remaining_time":16.59802781},
{"learn":[0.004322313649],"iteration":712,"passed_time":41.09535751,"remaining_time":16.54189005},
{"learn":[0.00431309786],"iteration":713,"passed_time":41.1563237,"remaining_time":16.48558624},
{"learn":[0.004307112852],"iteration":714,"passed_time":41.20973037,"remaining_time":16.42625616},
{"learn":[0.004301419594],"iteration":715,"passed_time":41.29386234,"remaining_time":16.37912976},
{"learn":[0.004294300581],"iteration":716,"passed_time":41.35615072,"remaining_time":16.32327846},
{"learn":[0.004289691797],"iteration":717,"passed_time":41.41418476,"remaining_time":16.2657383},
{"learn":[0.004281012827],"iteration":718,"passed_time":41.46771319,"remaining_time":16.20643589},
{"learn":[0.004276118872],"iteration":719,"passed_time":41.51656153,"remaining_time":16.14532948},
{"learn":[0.004270503791],"iteration":720,"passed_time":41.56938301,"remaining_time":16.08579454},
{"learn":[0.004264331396],"iteration":721,"passed_time":41.62185453,"remaining_time":16.02614343},
{"learn":[0.004250626214],"iteration":722,"passed_time":41.67083868,"remaining_time":15.96517609},
{"learn":[0.004244493239],"iteration":723,"passed_time":41.71806915,"remaining_time":15.90357332},
{"learn":[0.004237546145],"iteration":724,"passed_time":41.77334464,"remaining_time":15.84506176},
{"learn":[0.004233011872],"iteration":725,"passed_time":41.83131906,"remaining_time":15.78757772},
{"learn":[0.004227847812],"iteration":726,"passed_time":41.88822433,"remaining_time":15.72969084},
{"learn":[0.00422174052],"iteration":727,"passed_time":41.97618063,"remaining_time":15.68340815},
{"learn":[0.00421741397],"iteration":728,"passed_time":42.03189071,"remaining_time":15.62502385},
{"learn":[0.004212179289],"iteration":729,"passed_time":42.09260921,"remaining_time":15.5684993},
{"learn":[0.004207824881],"iteration":730,"passed_time":42.14538433,"remaining_time":15.5090402},
{"learn":[0.004200528146],"iteration":731,"passed_time":42.20048667,"remaining_time":15.4504514},
{"learn":[0.004187736325],"iteration":732,"passed_time":42.25224874,"remaining_time":15.39065541},
{"learn":[0.004182319349],"iteration":733,"passed_time":42.31158209,"remaining_time":15.33362512},
{"learn":[0.004176607811],"iteration":734,"passed_time":42.36348069,"remaining_time":15.273908},
{"learn":[0.004170953442],"iteration":735,"passed_time":42.41391835,"remaining_time":15.21368811},
{"learn":[0.004164516005],"iteration":736,"passed_time":42.45647513,"remaining_time":15.15068244},
{"learn":[0.004158260377],"iteration":737,"passed_time":42.50879713,"remaining_time":15.09119898},
{"learn":[0.004153909577],"iteration":738,"passed_time":42.55835846,"remaining_time":15.03075989},
{"learn":[0.004149393571],"iteration":739,"passed_time":42.61667404,"remaining_time":14.97342601},
{"learn":[0.004141437018],"iteration":740,"passed_time":42.66738367,"remaining_time":14.913431},
{"learn":[0.004136578703],"iteration":741,"passed_time":42.73265739,"remaining_time":14.85852508},
{"learn":[0.004130004448],"iteration":742,"passed_time":42.78626302,"remaining_time":14.79955531},
{"learn":[0.00412505247],"iteration":743,"passed_time":42.84424882,"remaining_time":14.74210712},
{"learn":[0.004118607885],"iteration":744,"passed_time":42.90265256,"remaining_time":14.68480054},
{"learn":[0.004111419096],"iteration":745,"passed_time":42.96081007,"remaining_time":14.62740718},
{"learn":[0.004103714207],"iteration":746,"passed_time":43.02971766,"remaining_time":14.5736527},
{"learn":[0.004099721217],"iteration":747,"passed_time":43.0835292,"remaining_time":14.51477187},
{"learn":[0.004094219566],"iteration":748,"passed_time":43.13797643,"remaining_time":14.4561176},
{"learn":[0.004088953526],"iteration":749,"passed_time":43.19634338,"remaining_time":14.39878113},
{"learn":[0.004083996736],"iteration":750,"passed_time":43.24814575,"remaining_time":14.33926537},
{"learn":[0.004079232725],"iteration":751,"passed_time":43.30787731,"remaining_time":14.28238507},
{"learn":[0.004075115005],"iteration":752,"passed_time":43.36050398,"remaining_time":14.22316665},
{"learn":[0.004069253784],"iteration":753,"passed_time":43.42246584,"remaining_time":14.1670114},
{"learn":[0.00406021472],"iteration":754,"passed_time":43.4762275,"remaining_time":14.10817978},
{"learn":[0.004051286681],"iteration":755,"passed_time":43.54406907,"remaining_time":14.05390589},
{"learn":[0.004046271334],"iteration":756,"passed_time":43.61476612,"remaining_time":14.00051277},
{"learn":[0.004042717502],"iteration":757,"passed_time":43.66324377,"remaining_time":13.9399802},
{"learn":[0.004037397771],"iteration":758,"passed_time":43.72208103,"remaining_time":13.88276881},
{"learn":[0.004031968025],"iteration":759,"passed_time":43.78870357,"remaining_time":13.82801165},
{"learn":[0.004028476169],"iteration":760,"passed_time":43.85935956,"remaining_time":13.77449006},
{"learn":[0.004017771521],"iteration":761,"passed_time":43.96108639,"remaining_time":13.73062803},
{"learn":[0.004011012927],"iteration":762,"passed_time":44.0237646,"remaining_time":13.6744852},
{"learn":[0.004006981794],"iteration":763,"passed_time":44.09546829,"remaining_time":13.62111324},
{"learn":[0.003996673699],"iteration":764,"passed_time":44.16236632,"remaining_time":13.56621711},
{"learn":[0.003991981475],"iteration":765,"passed_time":44.21946816,"remaining_time":13.50829706},
{"learn":[0.003988385696],"iteration":766,"passed_time":44.26749392,"remaining_time":13.44762201},
{"learn":[0.003982156226],"iteration":767,"passed_time":44.32718617,"remaining_time":13.39050416},
{"learn":[0.003977351129],"iteration":768,"passed_time":44.37748658,"remaining_time":13.33055839},
{"learn":[0.003972091333],"iteration":769,"passed_time":44.43362148,"remaining_time":13.27238044},
{"learn":[0.003967325887],"iteration":770,"passed_time":44.49034117,"remaining_time":13.21438149},
{"learn":[0.003962935889],"iteration":771,"passed_time":44.54045346,"remaining_time":13.15443444},
{"learn":[0.003955933155],"iteration":772,"passed_time":44.60261554,"remaining_time":13.0980514},
{"learn":[0.003949334391],"iteration":773,"passed_time":44.65670112,"remaining_time":13.03929516},
{"learn":[0.00394563294],"iteration":774,"passed_time":44.71422908,"remaining_time":12.98155038},
{"learn":[0.003940794292],"iteration":775,"passed_time":44.77166195,"remaining_time":12.92377871},
{"learn":[0.003935732154],"iteration":776,"passed_time":44.82350909,"remaining_time":12.8644048},
{"learn":[0.003928866969],"iteration":777,"passed_time":44.88607834,"remaining_time":12.80810976},
{"learn":[0.003923003083],"iteration":778,"passed_time":44.94262396,"remaining_time":12.75008973},
{"learn":[0.00391553572],"iteration":779,"passed_time":45.00728813,"remaining_time":12.69436332},
{"learn":[0.00391061497],"iteration":780,"passed_time":45.05542943,"remaining_time":12.63398085},
{"learn":[0.003905279293],"iteration":781,"passed_time":45.10458021,"remaining_time":12.57391111},
{"learn":[0.003901627942],"iteration":782,"passed_time":45.15226729,"remaining_time":12.5134636},
{"learn":[0.003897994443],"iteration":783,"passed_time":45.20044006,"remaining_time":12.45318247},
{"learn":[0.00389108642],"iteration":784,"passed_time":45.24918896,"remaining_time":12.39308997},
{"learn":[0.003887088364],"iteration":785,"passed_time":45.30715054,"remaining_time":12.33553462},
{"learn":[0.003878674881],"iteration":786,"passed_time":45.35715845,"remaining_time":12.2758256},
{"learn":[0.003868595578],"iteration":787,"passed_time":45.41536664,"remaining_time":12.21834737},
{"learn":[0.003864664644],"iteration":788,"passed_time":45.46828689,"remaining_time":12.15945315},
{"learn":[0.003858314506],"iteration":789,"passed_time":45.52183548,"remaining_time":12.10074108},
{"learn":[0.003851315891],"iteration":790,"passed_time":45.58222433,"remaining_time":12.04384941},
{"learn":[0.003848009319],"iteration":791,"passed_time":45.63445358,"remaining_time":11.98480599},
{"learn":[0.003841624298],"iteration":792,"passed_time":45.70278723,"remaining_time":11.92998355},
{"learn":[0.003835270258],"iteration":793,"passed_time":45.76405096,"remaining_time":11.87329282},
{"learn":[0.003829321276],"iteration":794,"passed_time":45.81449042,"remaining_time":11.81379942},
{"learn":[0.003820334572],"iteration":795,"passed_time":45.89822839,"remaining_time":11.76286255},
{"learn":[0.003813704984],"iteration":796,"passed_time":45.95491751,"remaining_time":11.7049539},
{"learn":[0.003806533443],"iteration":797,"passed_time":46.01926295,"remaining_time":11.64898636},
{"learn":[0.003803016468],"iteration":798,"passed_time":46.14516703,"remaining_time":11.60848382},
{"learn":[0.003799744582],"iteration":799,"passed_time":46.31492105,"remaining_time":11.57873026},
{"learn":[0.00379340724],"iteration":800,"passed_time":46.41255696,"remaining_time":11.53071016},
{"learn":[0.003785136418],"iteration":801,"passed_time":46.50071388,"remaining_time":11.48022612},
{"learn":[0.003781226667],"iteration":802,"passed_time":46.57854113,"remaining_time":11.42711408},
{"learn":[0.003775135388],"iteration":803,"passed_time":46.74827347,"remaining_time":11.39634527},
{"learn":[0.003770750219],"iteration":804,"passed_time":46.81565846,"remaining_time":11.34043901},
{"learn":[0.003767043362],"iteration":805,"passed_time":46.89767248,"remaining_time":11.28802539},
{"learn":[0.003762643676],"iteration":806,"passed_time":46.96278154,"remaining_time":11.23149546},
{"learn":[0.003754373075],"iteration":807,"passed_time":47.0293541,"remaining_time":11.17529206},
{"learn":[0.003750911836],"iteration":808,"passed_time":47.10174655,"remaining_time":11.12043707},
{"learn":[0.003746505792],"iteration":809,"passed_time":47.18116288,"remaining_time":11.06718635},
{"learn":[0.003740981213],"iteration":810,"passed_time":47.26251433,"remaining_time":11.01432208},
{"learn":[0.003737785478],"iteration":811,"passed_time":47.34570955,"remaining_time":10.96181453},
{"learn":[0.00373243873],"iteration":812,"passed_time":47.41166423,"remaining_time":10.90526594},
{"learn":[0.003727509999],"iteration":813,"passed_time":47.4757157,"remaining_time":10.84825936},
{"learn":[0.003724268217],"iteration":814,"passed_time":47.53945304,"remaining_time":10.79116419},
{"learn":[0.003720600296],"iteration":815,"passed_time":47.5976403,"remaining_time":10.73280124},
{"learn":[0.003715180467],"iteration":816,"passed_time":47.66223655,"remaining_time":10.67587428},
{"learn":[0.003711334901],"iteration":817,"passed_time":47.73787455,"remaining_time":10.62138529},
{"learn":[0.003707425087],"iteration":818,"passed_time":47.80792409,"remaining_time":10.5656096},
{"learn":[0.003696549293],"iteration":819,"passed_time":47.89081084,"remaining_time":10.51261701},
{"learn":[0.003693019704],"iteration":820,"passed_time":47.9631157,"remaining_time":10.45724447},
{"learn":[0.003689203167],"iteration":821,"passed_time":48.04495156,"remaining_time":10.40389462},
{"learn":[0.003683847892],"iteration":822,"passed_time":48.11934612,"remaining_time":10.34887517},
{"learn":[0.003679542221],"iteration":823,"passed_time":48.1991611,"remaining_time":10.29496645},
{"learn":[0.003675216076],"iteration":824,"passed_time":48.29026546,"remaining_time":10.24338964},
{"learn":[0.003667470434],"iteration":825,"passed_time":48.35939066,"remaining_time":10.18708714},
{"learn":[0.003660938822],"iteration":826,"passed_time":48.42546388,"remaining_time":10.13011518},
{"learn":[0.003654460661],"iteration":827,"passed_time":48.49155597,"remaining_time":10.07312515},
{"learn":[0.003649982811],"iteration":828,"passed_time":48.55554793,"remaining_time":10.01567997},
{"learn":[0.003646176019],"iteration":829,"passed_time":48.62276776,"remaining_time":9.958880143},
{"learn":[0.003639419515],"iteration":830,"passed_time":48.68720904,"remaining_time":9.901490166},
{"learn":[0.003633006686],"iteration":831,"passed_time":48.75221987,"remaining_time":9.844198243},
{"learn":[0.003627887572],"iteration":832,"passed_time":48.83672653,"remaining_time":9.790796315},
{"learn":[0.003624216238],"iteration":833,"passed_time":48.90324448,"remaining_time":9.73373931},
{"learn":[0.00362032969],"iteration":834,"passed_time":48.98506465,"remaining_time":9.679683435},
{"learn":[0.003614485175],"iteration":835,"passed_time":49.05916677,"remaining_time":9.62404707},
{"learn":[0.003611338191],"iteration":836,"passed_time":49.1393651,"remaining_time":9.569553777},
{"learn":[0.003607337935],"iteration":837,"passed_time":49.21393528,"remaining_time":9.513911116},
{"learn":[0.003603771283],"iteration":838,"passed_time":49.28676645,"remaining_time":9.457889629},
{"learn":[0.00359893868],"iteration":839,"passed_time":49.36573778,"remaining_time":9.402997672},
{"learn":[0.003595351503],"iteration":840,"passed_time":49.44801938,"remaining_time":9.348674295},
{"learn":[0.003589722041],"iteration":841,"passed_time":49.5177857,"remaining_time":9.291936033},
{"learn":[0.003585578845],"iteration":842,"passed_time":49.58620026,"remaining_time":9.234915114},
{"learn":[0.003581664042],"iteration":843,"passed_time":49.65245893,"remaining_time":9.177468712},
{"learn":[0.003577505613],"iteration":844,"passed_time":49.71546707,"remaining_time":9.119405203},
{"learn":[0.003573094222],"iteration":845,"passed_time":49.77900654,"remaining_time":9.061426723},
{"learn":[0.003570003885],"iteration":846,"passed_time":49.84522608,"remaining_time":9.003919233},
{"learn":[0.003566250237],"iteration":847,"passed_time":49.90367981,"remaining_time":8.944999211},
{"learn":[0.003560965242],"iteration":848,"passed_time":49.96695476,"remaining_time":8.886937773},
{"learn":[0.00355634905],"iteration":849,"passed_time":50.03259103,"remaining_time":8.829280769},
{"learn":[0.003552366555],"iteration":850,"passed_time":50.10398772,"remaining_time":8.772613597},
{"learn":[0.003549748786],"iteration":851,"passed_time":50.17562042,"remaining_time":8.715952843},
{"learn":[0.003545559097],"iteration":852,"passed_time":50.23166999,"remaining_time":8.656571498},
{"learn":[0.003541453867],"iteration":853,"passed_time":50.30077274,"remaining_time":8.599429532},
{"learn":[0.003537456613],"iteration":854,"passed_time":50.37809665,"remaining_time":8.543653817},
{"learn":[0.003531958034],"iteration":855,"passed_time":50.44633624,"remaining_time":8.486299554},
{"learn":[0.003526637195],"iteration":856,"passed_time":50.51004321,"remaining_time":8.42816357},
{"learn":[0.003522161825],"iteration":857,"passed_time":50.5660031,"remaining_time":8.368732448},
{"learn":[0.003515030271],"iteration":858,"passed_time":50.62899488,"remaining_time":8.310463654},
{"learn":[0.003508625666],"iteration":859,"passed_time":50.69151054,"remaining_time":8.252106367},
{"learn":[0.00350267351],"iteration":860,"passed_time":50.74966227,"remaining_time":8.193034907},
{"learn":[0.003497090424],"iteration":861,"passed_time":50.81148867,"remaining_time":8.13455387},
{"learn":[0.003493528261],"iteration":862,"passed_time":50.87594855,"remaining_time":8.076483141},
{"learn":[0.003488277012],"iteration":863,"passed_time":50.93123994,"remaining_time":8.016954435},
{"learn":[0.003480073672],"iteration":864,"passed_time":51.00368576,"remaining_time":7.960112806},
{"learn":[0.003470006721],"iteration":865,"passed_time":51.07371081,"remaining_time":7.902860563},
{"learn":[0.003460426085],"iteration":866,"passed_time":51.138534,"remaining_time":7.844780878},
{"learn":[0.003455643539],"iteration":867,"passed_time":51.19592668,"remaining_time":7.78555567},
{"learn":[0.003450969649],"iteration":868,"passed_time":51.25291325,"remaining_time":7.726273458},
{"learn":[0.00344148703],"iteration":869,"passed_time":51.30855362,"remaining_time":7.666795368},
{"learn":[0.003437774806],"iteration":870,"passed_time":51.37305247,"remaining_time":7.608638082},
{"learn":[0.00343435109],"iteration":871,"passed_time":51.43736473,"remaining_time":7.55043886},
{"learn":[0.003430455351],"iteration":872,"passed_time":51.50377591,"remaining_time":7.492530974},
{"learn":[0.003423154537],"iteration":873,"passed_time":51.56079166,"remaining_time":7.433249141},
{"learn":[0.003417808314],"iteration":874,"passed_time":51.62427325,"remaining_time":7.374896178},
{"learn":[0.003414651045],"iteration":875,"passed_time":51.69035787,"remaining_time":7.316899972},
{"learn":[0.003409199925],"iteration":876,"passed_time":51.78261771,"remaining_time":7.262556417},
{"learn":[0.003406728798],"iteration":877,"passed_time":51.86512719,"remaining_time":7.20677166},
{"learn":[0.003397022582],"iteration":878,"passed_time":51.97418284,"remaining_time":7.154580346},
{"learn":[0.003394101207],"iteration":879,"passed_time":52.1051699,"remaining_time":7.105250441},
{"learn":[0.00339088644],"iteration":880,"passed_time":52.2231817,"remaining_time":7.053982546},
{"learn":[0.003385544244],"iteration":881,"passed_time":52.30722571,"remaining_time":6.99801886},
{"learn":[0.003380863133],"iteration":882,"passed_time":52.37841491,"remaining_time":6.940288272},
{"learn":[0.003377013529],"iteration":883,"passed_time":52.44776643,"remaining_time":6.882286093},
{"learn":[0.00337312998],"iteration":884,"passed_time":52.51766626,"remaining_time":6.824329514},
{"learn":[0.003370712229],"iteration":885,"passed_time":52.58428265,"remaining_time":6.765923501},
{"learn":[0.003367501738],"iteration":886,"passed_time":52.65280557,"remaining_time":6.70774186},
{"learn":[0.003364639709],"iteration":887,"passed_time":52.71752606,"remaining_time":6.64905734},
{"learn":[0.003361466887],"iteration":888,"passed_time":52.79076803,"remaining_time":6.59142323},
{"learn":[0.003357815224],"iteration":889,"passed_time":52.85750294,"remaining_time":6.532949801},
{"learn":[0.003353580735],"iteration":890,"passed_time":52.93521594,"remaining_time":6.475800827},
{"learn":[0.003349114633],"iteration":891,"passed_time":53.01852337,"remaining_time":6.419283099},
{"learn":[0.003345694035],"iteration":892,"passed_time":53.097401,"remaining_time":6.362174587},
{"learn":[0.00333854049],"iteration":893,"passed_time":53.17812284,"remaining_time":6.305236041},
{"learn":[0.003336161304],"iteration":894,"passed_time":53.25151888,"remaining_time":6.247384896},
{"learn":[0.003332799334],"iteration":895,"passed_time":53.32712221,"remaining_time":6.189755256},
{"learn":[0.003326673415],"iteration":896,"passed_time":53.39821318,"remaining_time":6.1315674},
{"learn":[0.003324259381],"iteration":897,"passed_time":53.46548236,"remaining_time":6.072916704},
{"learn":[0.003320119598],"iteration":898,"passed_time":53.53172085,"remaining_time":6.014131041},
{"learn":[0.003313761777],"iteration":899,"passed_time":53.60051474,"remaining_time":5.955612749},
{"learn":[0.00330742446],"iteration":900,"passed_time":53.66620725,"remaining_time":5.896730874},
{"learn":[0.003303941747],"iteration":901,"passed_time":53.73846885,"remaining_time":5.838547614},
{"learn":[0.003299360341],"iteration":902,"passed_time":53.81594095,"remaining_time":5.780892881},
{"learn":[0.003290796522],"iteration":903,"passed_time":53.89249731,"remaining_time":5.723097059},
{"learn":[0.003287234077],"iteration":904,"passed_time":53.96467225,"remaining_time":5.66479985},
{"learn":[0.003284230159],"iteration":905,"passed_time":54.03378283,"remaining_time":5.606154068},
{"learn":[0.003280268653],"iteration":906,"passed_time":54.10196236,"remaining_time":5.547389746},
{"learn":[0.003276543149],"iteration":907,"passed_time":54.17001515,"remaining_time":5.488591843},
{"learn":[0.003272867273],"iteration":908,"passed_time":54.2488433,"remaining_time":5.430852299},
{"learn":[0.003270042923],"iteration":909,"passed_time":54.32328543,"remaining_time":5.372632625},
{"learn":[0.003267439531],"iteration":910,"passed_time":54.40612008,"remaining_time":5.315197241},
{"learn":[0.003263383776],"iteration":911,"passed_time":54.47278537,"remaining_time":5.256145957},
{"learn":[0.003257379831],"iteration":912,"passed_time":54.54697565,"remaining_time":5.197795051},
{"learn":[0.003252846925],"iteration":913,"passed_time":54.60916556,"remaining_time":5.138280348},
{"learn":[0.003248403481],"iteration":914,"passed_time":54.67465326,"remaining_time":5.079066149},
{"learn":[0.003243993586],"iteration":915,"passed_time":54.73354116,"remaining_time":5.019233032},
{"learn":[0.003241694908],"iteration":916,"passed_time":54.7946232,"remaining_time":4.959600573},
{"learn":[0.003238915065],"iteration":917,"passed_time":54.85659946,"remaining_time":4.900044832},
{"learn":[0.003234687882],"iteration":918,"passed_time":54.92261464,"remaining_time":4.840839811},
{"learn":[0.00323109618],"iteration":919,"passed_time":54.97565301,"remaining_time":4.780491566},
{"learn":[0.003226355729],"iteration":920,"passed_time":55.03984211,"remaining_time":4.721115664},
{"learn":[0.003222348711],"iteration":921,"passed_time":55.0943755,"remaining_time":4.660912461},
{"learn":[0.003218027183],"iteration":922,"passed_time":55.15853648,"remaining_time":4.601524712},
{"learn":[0.003215205341],"iteration":923,"passed_time":55.22785043,"remaining_time":4.542550469},
{"learn":[0.003212997096],"iteration":924,"passed_time":55.28899508,"remaining_time":4.482891493},
{"learn":[0.003208764968],"iteration":925,"passed_time":55.34411888,"remaining_time":4.422748161},
{"learn":[0.003203802614],"iteration":926,"passed_time":55.4066124,"remaining_time":4.363196014},
{"learn":[0.00320028087],"iteration":927,"passed_time":55.46040044,"remaining_time":4.302962103},
{"learn":[0.003195721296],"iteration":928,"passed_time":55.52151373,"remaining_time":4.24330191},
{"learn":[0.003193058757],"iteration":929,"passed_time":55.57491338,"remaining_time":4.183057996},
{"learn":[0.003187724344],"iteration":930,"passed_time":55.64274454,"remaining_time":4.12389836},
{"learn":[0.00318120961],"iteration":931,"passed_time":55.70247435,"remaining_time":4.06412903},
{"learn":[0.003177789253],"iteration":932,"passed_time":55.75785032,"remaining_time":4.004047129},
{"learn":[0.003174413583],"iteration":933,"passed_time":55.82321123,"remaining_time":3.944680879},
{"learn":[0.003166847869],"iteration":934,"passed_time":55.87581086,"remaining_time":3.884414659},
{"learn":[0.003161142703],"iteration":935,"passed_time":55.94665723,"remaining_time":3.82541246},
{"learn":[0.003157334764],"iteration":936,"passed_time":56.00870008,"remaining_time":3.765793069},
{"learn":[0.003152471615],"iteration":937,"passed_time":56.07157556,"remaining_time":3.706223545},
{"learn":[0.003147809137],"iteration":938,"passed_time":56.13577672,"remaining_time":3.646733099},
{"learn":[0.003144036556],"iteration":939,"passed_time":56.1909107,"remaining_time":3.586653874},
{"learn":[0.00314145964],"iteration":940,"passed_time":56.25404626,"remaining_time":3.527086854},
{"learn":[0.003138349599],"iteration":941,"passed_time":56.30870064,"remaining_time":3.466990061},
{"learn":[0.003135531984],"iteration":942,"passed_time":56.3683136,"remaining_time":3.407204534},
{"learn":[0.003128618145],"iteration":943,"passed_time":56.42552965,"remaining_time":3.347277183},
{"learn":[0.003123704725],"iteration":944,"passed_time":56.48830605,"remaining_time":3.287679188},
{"learn":[0.003119536869],"iteration":945,"passed_time":56.54877967,"remaining_time":3.227943026},
{"learn":[0.00311240213],"iteration":946,"passed_time":56.61148386,"remaining_time":3.168330142},
{"learn":[0.003108444242],"iteration":947,"passed_time":56.66676948,"remaining_time":3.108303811},
{"learn":[0.003101280708],"iteration":948,"passed_time":56.73216294,"remaining_time":3.048830674},
{"learn":[0.003097901472],"iteration":949,"passed_time":56.80601447,"remaining_time":2.989790236},
{"learn":[0.003095068381],"iteration":950,"passed_time":56.88224906,"remaining_time":2.930841434},
{"learn":[0.003089880884],"iteration":951,"passed_time":56.93506238,"remaining_time":2.870675414},
{"learn":[0.003086293559],"iteration":952,"passed_time":56.98439701,"remaining_time":2.810353263},
{"learn":[0.003084507414],"iteration":953,"passed_time":57.03699692,"remaining_time":2.750211591},
{"learn":[0.003081625727],"iteration":954,"passed_time":57.08605178,"remaining_time":2.68991867},
{"learn":[0.00307896912],"iteration":955,"passed_time":57.13575157,"remaining_time":2.629678943},
{"learn":[0.003075803997],"iteration":956,"passed_time":57.18279951,"remaining_time":2.569342089},
{"learn":[0.003073333066],"iteration":957,"passed_time":57.22788277,"remaining_time":2.508946844},
{"learn":[0.003071198076],"iteration":958,"passed_time":57.27661036,"remaining_time":2.448739338},
{"learn":[0.003068050694],"iteration":959,"passed_time":57.3254799,"remaining_time":2.388561662},
{"learn":[0.003065335997],"iteration":960,"passed_time":57.37072378,"remaining_time":2.328260382},
{"learn":[0.003062188498],"iteration":961,"passed_time":57.41952068,"remaining_time":2.268130755},
{"learn":[0.003058206343],"iteration":962,"passed_time":57.46296584,"remaining_time":2.207819041},
{"learn":[0.003055284782],"iteration":963,"passed_time":57.50930856,"remaining_time":2.147650527},
{"learn":[0.003047636718],"iteration":964,"passed_time":57.55699256,"remaining_time":2.087559316},
{"learn":[0.003042837892],"iteration":965,"passed_time":57.60648509,"remaining_time":2.027557446},
{"learn":[0.003037595269],"iteration":966,"passed_time":57.66067334,"remaining_time":1.96773756},
{"learn":[0.003033933833],"iteration":967,"passed_time":57.70738221,"remaining_time":1.907682057},
{"learn":[0.003030295047],"iteration":968,"passed_time":57.75952663,"remaining_time":1.847827993},
{"learn":[0.003027613446],"iteration":969,"passed_time":57.81379108,"remaining_time":1.788055394},
{"learn":[0.003025611259],"iteration":970,"passed_time":57.86522306,"remaining_time":1.728209546},
{"learn":[0.003022864623],"iteration":971,"passed_time":57.91697839,"remaining_time":1.668390324},
{"learn":[0.003019547698],"iteration":972,"passed_time":57.97226694,"remaining_time":1.608685722},
{"learn":[0.003017630675],"iteration":973,"passed_time":58.03001697,"remaining_time":1.549055895},
{"learn":[0.0030152348],"iteration":974,"passed_time":58.07982153,"remaining_time":1.489226193},
{"learn":[0.003012183694],"iteration":975,"passed_time":58.12937427,"remaining_time":1.429410843},
{"learn":[0.003009998919],"iteration":976,"passed_time":58.1987326,"remaining_time":1.370082753},
{"learn":[0.003007828778],"iteration":977,"passed_time":58.29737275,"remaining_time":1.311392843},
{"learn":[0.003004533378],"iteration":978,"passed_time":58.3643984,"remaining_time":1.251943173},
{"learn":[0.00300116735],"iteration":979,"passed_time":58.41188839,"remaining_time":1.192079355},
{"learn":[0.002997028957],"iteration":980,"passed_time":58.45918466,"remaining_time":1.132237012},
{"learn":[0.002994838159],"iteration":981,"passed_time":58.50863042,"remaining_time":1.072459621},
{"learn":[0.002989586303],"iteration":982,"passed_time":58.5523832,"remaining_time":1.012604796},
{"learn":[0.002987191998],"iteration":983,"passed_time":58.6039289,"remaining_time":0.9529094129},
{"learn":[0.002984150611],"iteration":984,"passed_time":58.64572092,"remaining_time":0.8930820444},
{"learn":[0.002981317742],"iteration":985,"passed_time":58.6945879,"remaining_time":0.8333917147},
{"learn":[0.002979127836],"iteration":986,"passed_time":58.77984322,"remaining_time":0.7742025955},
{"learn":[0.002976423807],"iteration":987,"passed_time":58.867098,"remaining_time":0.7149849959},
{"learn":[0.002973894074],"iteration":988,"passed_time":58.92775888,"remaining_time":0.6554149117},
{"learn":[0.002969859763],"iteration":989,"passed_time":58.98761705,"remaining_time":0.5958345156},
{"learn":[0.002964540388],"iteration":990,"passed_time":59.04465871,"remaining_time":0.5362279802},
{"learn":[0.002961847836],"iteration":991,"passed_time":59.10298447,"remaining_time":0.4766369715},
{"learn":[0.002957295798],"iteration":992,"passed_time":59.16979941,"remaining_time":0.4171083544},
{"learn":[0.002955231414],"iteration":993,"passed_time":59.24171078,"remaining_time":0.3575958397},
{"learn":[0.002952292537],"iteration":994,"passed_time":59.32961966,"remaining_time":0.2981387923},
{"learn":[0.00295017573],"iteration":995,"passed_time":59.4049076,"remaining_time":0.2385739261},
{"learn":[0.002948093373],"iteration":996,"passed_time":59.49256846,"remaining_time":0.1790147496},
{"learn":[0.00294592462],"iteration":997,"passed_time":59.57136837,"remaining_time":0.1193814997},
{"learn":[0.00294196442],"iteration":998,"passed_time":59.65831988,"remaining_time":0.05971803791},
{"learn":[0.002938977612],"iteration":999,"passed_time":59.74174015,"remaining_time":0}
]}